{
  "category": "Data Sources",
  "content": "\"\"\"Documentation for Load Object\n\n# Load an Object from the object Repository\n\n## Description\nSerialize an Object and store it in the object Repository.\n\n## Inputs\n* **name** (String): The name for the Object.\n* **tag** (String): The tag for the Object.\n\n## Outputs\n* **obt** (Integer, Float, Pandas Series or Pandas DataFrame): The object to load. \n\n# Load an Object from the object Repository\n\nHetida Designer comes with a simple object store to allow serialization and persistence of Python objects between Workflows and Workflow Executions. A typical use case is storing of a trained machine learning model in a training workflow and loading it in a prediction workflow.\n\nTechnically joblib is used for serialization in order to efficiently store numpy arrays and Pandas objects.\n\nThe serialized object is stored using the name and a tag. It can be retrieved using the same name and tag combination. Additionally there is a magic \"latest\" tag which retrieves the last stored object with that name.\n\"\"\"\n\n# add your own imports here\nimport hetdesrun.serialization\n\n# ***** DO NOT EDIT LINES BELOW *****\n# These lines may be overwritten if component details or inputs/outputs change.\nCOMPONENT_INFO = {\n    \"inputs\": {\n        \"name\": {\"data_type\": \"STRING\"},\n        \"tag\": {\"data_type\": \"STRING\"},\n    },\n    \"outputs\": {\n        \"obj\": {\"data_type\": \"ANY\"},\n    },\n    \"name\": \"Load Object\",\n    \"category\": \"Data Sources\",\n    \"description\": \"Load a serialized Object from the object Repository\",\n    \"version_tag\": \"1.0.0\",\n    \"id\": \"eb8e8d6b-ba7d-dc88-14dc-6839a471d5e0\",\n    \"revision_group_id\": \"eb8e8d6b-ba7d-dc88-14dc-6839a471d5e0\",\n    \"state\": \"RELEASED\",\n    \"released_timestamp\": \"2022-02-09T17:33:29.147709+00:00\",\n}\n\nfrom hdutils import parse_default_value  # noqa: E402, F401\n\n\ndef main(*, name, tag):\n    # entrypoint function for this component\n    # ***** DO NOT EDIT LINES ABOVE *****\n    # write your function code here.\n    return {\"obj\": hetdesrun.serialization.load_obj(name, tag)}\n\n\nTEST_WIRING_FROM_PY_FILE_IMPORT = {}\nRELEASE_WIRING = {}\n",
  "description": "Load a serialized Object from the object Repository",
  "documentation": "# Load an Object from the object Repository\n\n## Description\nSerialize an Object and store it in the object Repository.\n\n## Inputs\n* **name** (String): The name for the Object.\n* **tag** (String): The tag for the Object.\n\n## Outputs\n* **obt** (Integer, Float, Pandas Series or Pandas DataFrame): The object to load. \n\n# Load an Object from the object Repository\n\nHetida Designer comes with a simple object store to allow serialization and persistence of Python objects between Workflows and Workflow Executions. A typical use case is storing of a trained machine learning model in a training workflow and loading it in a prediction workflow.\n\nTechnically joblib is used for serialization in order to efficiently store numpy arrays and Pandas objects.\n\nThe serialized object is stored using the name and a tag. It can be retrieved using the same name and tag combination. Additionally there is a magic \"latest\" tag which retrieves the last stored object with that name.\n",
  "id": "eb8e8d6b-ba7d-dc88-14dc-6839a471d5e0",
  "io_interface": {
    "inputs": [
      {
        "data_type": "STRING",
        "id": "562eea2c-2f89-ebe5-f62a-658b561f25be",
        "name": "name",
        "type": "REQUIRED"
      },
      {
        "data_type": "STRING",
        "id": "f1a2390f-1bae-62a7-731b-4772c0ba6708",
        "name": "tag",
        "type": "REQUIRED"
      }
    ],
    "outputs": [
      {
        "data_type": "ANY",
        "id": "2a5d344e-53b3-cf7e-2e05-eda8ea17fe89",
        "name": "obj"
      }
    ]
  },
  "name": "Load Object",
  "release_wiring": {
    "dashboard_positionings": [],
    "input_wirings": [],
    "output_wirings": []
  },
  "released_timestamp": "2022-02-09T17:33:29.147709+00:00",
  "revision_group_id": "eb8e8d6b-ba7d-dc88-14dc-6839a471d5e0",
  "state": "RELEASED",
  "test_wiring": {
    "dashboard_positionings": [],
    "input_wirings": [],
    "output_wirings": []
  },
  "type": "COMPONENT",
  "version_tag": "1.0.0"
}