{
  "category": "Arithmetic",
  "content": "\"\"\"Documentation for Sqrt\n\n# Sqrt\n\n## Description\nThis component calculates the square root for numeric values, Pandas Series and Pandas DataFrames.\n\n## Inputs\n* **data** (Integer, Float, Pandas Series or Pandas DataFrame): Entries must be numeric.\n\n## Outputs\n* **sqrt** (Integer, Float, Pandas Series or Pandas DataFrame): The square root of data.\n\n## Details\nThe component calculates the square root. \n\n## Examples\nThe json input of a typical call of this component with a Pandas Series is\n```\n{\n\t\"data\": {\n\t\t\t\t\"2019-08-01T15:20:12\": 4,\n\t\t\t\t\"2019-08-01T15:44:12\": 9,\n\t\t\t\t\"2019-08-03T16:20:15\": 0,\n\t\t\t\t\"2019-08-05T12:00:34\": 1,\n             \t\t\t\"2019-08-07T11:01:00\": 100\n\t}\n}\n```\nThe expected output is\n```\n\t\"sqrt\": {\n\t\t\t\"2019-08-01T15:20:12\": 2,\n\t\t\t\"2019-08-01T15:44:12\": 3,\n\t\t\t\"2019-08-03T16:20:15\": 0,\n\t\t\t\"2019-08-05T12:00:34\": 1,\n                       \"2019-08-07T11:01:00\": 10  \n\t}\n\n```\n\nThe json input of a typical call of this component with a Pandas DataFrame is\n```\n{\n    \"data\": {\n\t\t\t\"a\": {\n           \t\t        \"2019-08-01T15:20:12\": 1,\n\t\t\t\t\"2019-08-01T15:44:12\": null,\n\t\t\t\t\"2019-08-03T16:20:15\": 100,\n\t\t\t\t\"2019-08-05T12:00:34\": 6.25\n             },\n        \t\t\"b\": {\n                                \"2019-08-01T15:20:12\": 4,\n\t\t\t\t \"2019-08-01T15:44:12\": 0,\n\t\t\t\t \"2019-08-03T16:20:15\": 25,\n\t\t\t\t \"2019-08-05T12:00:34\": 625\n             }\n\t}\n}\n```\nThe expected output is\n```\n\t\"sqrt\": {\n\t\t\t\"a\": {\n                               \"2019-08-01T15:20:12\": 1,\n\t\t\t\t\"2019-08-01T15:44:12\": null,\n\t\t\t\t\"2019-08-03T16:20:15\": 10,\n\t\t\t\t\"2019-08-05T12:00:34\": 2.5\n             },\n          \t        \"b\": {\n                \t         \"2019-08-01T15:20:12\": 2,\n\t\t\t\t \"2019-08-01T15:44:12\": 0,\n\t\t\t\t \"2019-08-03T16:20:15\": 5,\n\t\t\t\t \"2019-08-05T12:00:34\": 25\n             }\n\t}\n```\n\"\"\"\n\nimport pandas as pd\nimport numpy as np\n\n# ***** DO NOT EDIT LINES BELOW *****\n# These lines may be overwritten if component details or inputs/outputs change.\nCOMPONENT_INFO = {\n    \"inputs\": {\n        \"data\": {\"data_type\": \"ANY\"},\n    },\n    \"outputs\": {\n        \"sqrt\": {\"data_type\": \"ANY\"},\n    },\n    \"name\": \"Sqrt\",\n    \"category\": \"Arithmetic\",\n    \"description\": \"Calculates the square root\",\n    \"version_tag\": \"1.0.0\",\n    \"id\": \"40a03a56-5e3d-2695-07e4-9bcf0b1c3a39\",\n    \"revision_group_id\": \"40a03a56-5e3d-2695-07e4-9bcf0b1c3a39\",\n    \"state\": \"RELEASED\",\n    \"released_timestamp\": \"2022-02-09T17:33:32.169008+00:00\",\n}\n\nfrom hdutils import parse_default_value  # noqa: E402, F401\n\n\ndef main(*, data):\n    # entrypoint function for this component\n    # ***** DO NOT EDIT LINES ABOVE *****\n    # write your function code here.\n\n    return {\"sqrt\": np.sqrt(data)}\n\n\nTEST_WIRING_FROM_PY_FILE_IMPORT = {}\n",
  "description": "Calculates the square root",
  "documentation": "# Sqrt\n\n## Description\nThis component calculates the square root for numeric values, Pandas Series and Pandas DataFrames.\n\n## Inputs\n* **data** (Integer, Float, Pandas Series or Pandas DataFrame): Entries must be numeric.\n\n## Outputs\n* **sqrt** (Integer, Float, Pandas Series or Pandas DataFrame): The square root of data.\n\n## Details\nThe component calculates the square root. \n\n## Examples\nThe json input of a typical call of this component with a Pandas Series is\n```\n{\n\t\"data\": {\n\t\t\t\t\"2019-08-01T15:20:12\": 4,\n\t\t\t\t\"2019-08-01T15:44:12\": 9,\n\t\t\t\t\"2019-08-03T16:20:15\": 0,\n\t\t\t\t\"2019-08-05T12:00:34\": 1,\n             \t\t\t\"2019-08-07T11:01:00\": 100\n\t}\n}\n```\nThe expected output is\n```\n\t\"sqrt\": {\n\t\t\t\"2019-08-01T15:20:12\": 2,\n\t\t\t\"2019-08-01T15:44:12\": 3,\n\t\t\t\"2019-08-03T16:20:15\": 0,\n\t\t\t\"2019-08-05T12:00:34\": 1,\n                       \"2019-08-07T11:01:00\": 10  \n\t}\n\n```\n\nThe json input of a typical call of this component with a Pandas DataFrame is\n```\n{\n    \"data\": {\n\t\t\t\"a\": {\n           \t\t        \"2019-08-01T15:20:12\": 1,\n\t\t\t\t\"2019-08-01T15:44:12\": null,\n\t\t\t\t\"2019-08-03T16:20:15\": 100,\n\t\t\t\t\"2019-08-05T12:00:34\": 6.25\n             },\n        \t\t\"b\": {\n                                \"2019-08-01T15:20:12\": 4,\n\t\t\t\t \"2019-08-01T15:44:12\": 0,\n\t\t\t\t \"2019-08-03T16:20:15\": 25,\n\t\t\t\t \"2019-08-05T12:00:34\": 625\n             }\n\t}\n}\n```\nThe expected output is\n```\n\t\"sqrt\": {\n\t\t\t\"a\": {\n                               \"2019-08-01T15:20:12\": 1,\n\t\t\t\t\"2019-08-01T15:44:12\": null,\n\t\t\t\t\"2019-08-03T16:20:15\": 10,\n\t\t\t\t\"2019-08-05T12:00:34\": 2.5\n             },\n          \t        \"b\": {\n                \t         \"2019-08-01T15:20:12\": 2,\n\t\t\t\t \"2019-08-01T15:44:12\": 0,\n\t\t\t\t \"2019-08-03T16:20:15\": 5,\n\t\t\t\t \"2019-08-05T12:00:34\": 25\n             }\n\t}\n```\n",
  "id": "40a03a56-5e3d-2695-07e4-9bcf0b1c3a39",
  "io_interface": {
    "inputs": [
      {
        "data_type": "ANY",
        "id": "bc209f5e-c11c-181e-e026-92ee60714c94",
        "name": "data",
        "type": "REQUIRED"
      }
    ],
    "outputs": [
      {
        "data_type": "ANY",
        "id": "5b535a18-0914-34ae-7d74-3368782df395",
        "name": "sqrt"
      }
    ]
  },
  "name": "Sqrt",
  "released_timestamp": "2022-02-09T17:33:32.169008+00:00",
  "revision_group_id": "40a03a56-5e3d-2695-07e4-9bcf0b1c3a39",
  "state": "RELEASED",
  "test_wiring": {
    "dashboard_positionings": [],
    "input_wirings": [],
    "output_wirings": []
  },
  "type": "COMPONENT",
  "version_tag": "1.0.0"
}