{
  "category": "Models",
  "content": "import tensorflow as tf\n\n\n# ***** DO NOT EDIT LINES BELOW *****\n# These lines may be overwritten if component details or inputs/outputs change.\nCOMPONENT_INFO = {\n    \"inputs\": {\n        \"AntirectifierLayer\": \"ANY\",\n    },\n    \"outputs\": {\n        \"model\": \"ANY\",\n    },\n    \"name\": \"Build Model with AntirectifierLayer\",\n    \"category\": \"Models\",\n    \"description\": \"Build model with AntirectifierLayer\",\n    \"version_tag\": \"0.1.1\",\n    \"id\": \"5e425f2f-8893-44c0-8df2-df426d53e888\",\n    \"revision_group_id\": \"cab79db8-932e-4727-9010-8c38c658d8b5\",\n    \"state\": \"RELEASED\",\n    \"released_timestamp\": \"2023-04-04T14:55:09.197871+00:00\",\n}\n\n\ndef main(*, AntirectifierLayer):\n    # entrypoint function for this component\n    # ***** DO NOT EDIT LINES ABOVE *****\n    model = tf.keras.Sequential(\n        [\n            tf.keras.Input(shape=(784,)),\n            tf.keras.layers.Dense(256),\n            AntirectifierLayer(),\n            tf.keras.layers.Dense(256),\n            AntirectifierLayer(),\n            tf.keras.layers.Dropout(0.5),\n            tf.keras.layers.Dense(10),\n        ]\n    )\n    return {\"model\": model}",
  "description": "Build model with AntirectifierLayer",
  "documentation": "# New Component/Workflow\n## Description\n## Inputs\n## Outputs\n## Details\n## Examples\n",
  "id": "5e425f2f-8893-44c0-8df2-df426d53e888",
  "io_interface": {
    "inputs": [
      {
        "data_type": "ANY",
        "id": "5e2a577c-3bf5-49a2-ba8e-fa5fd552ed97",
        "name": "AntirectifierLayer"
      }
    ],
    "outputs": [
      {
        "data_type": "ANY",
        "id": "a438326f-045b-403c-bf28-7810bf05faba",
        "name": "model"
      }
    ]
  },
  "name": "Build Model with AntirectifierLayer",
  "released_timestamp": "2023-04-04T14:55:09.197871+00:00",
  "revision_group_id": "cab79db8-932e-4727-9010-8c38c658d8b5",
  "state": "RELEASED",
  "test_wiring": {
    "input_wirings": [],
    "output_wirings": []
  },
  "type": "COMPONENT",
  "version_tag": "0.1.1"
}