{
  "category": "Statistic",
  "content": "\"\"\"Documentation for Average\n\n# Average\n\n## Description\nThis component calculates the average of the input.\n\n## Inputs\n* **data** (Pandas Series or Pandas DataFrame): Entries must be numeric.\n\n## Outputs\n* **average** (Float or Pandas Series): The average of **data**. \n\n## Details\nThe component calculates the average of the columns of **data**, excluding NaN respectively None values. \n\nColumns including non-numeric values are ignored. \n\n## Examples\nThe json input of a typical call of this component with a Pandas Series is\n```\n{\n\t\"data\": {\n\t\t\t\t\"2019-08-01T15:20:10\": 1.7,\n\t\t\t\t\"2019-08-01T15:20:20\": null,\n\t\t\t\t\"2019-08-01T15:20:25\": 0.3,\n\t\t\t\t\"2019-08-01T15:20:30\": 1.0\n\t}\n}\n```\nThe expected output is\n```\n\t\"average\": 1 \n```\nThe json input of a typical call of this component with a Pandas DataFrame is\n```\n{\n\t\"data\": {\n\t\t\t\t\"a\": {\n                    \"2019-08-01T15:44:12\": 9,\n                    \"2019-08-01T15:20:12\": -4,\n                    \"2019-08-03T16:20:15\": None,\n                    \"2019-08-05T12:00:34\": 1,\n                },\n                \"b\": {\n                    \"2019-08-01T15:44:12\": -1,\n                    \"2019-08-01T15:20:12\": \"test\",\n                    \"2019-08-03T16:20:15\": 0,\n                    \"2019-08-05T12:00:34\": 4,\n                }\n\t}\n}\n```\nThe expected output is\n```\n\t\"average\": {\n\t\t\t\t\"a\": 2\n\t}\n```\n\"\"\"\n\nimport pandas as pd\n\n# ***** DO NOT EDIT LINES BELOW *****\n# These lines may be overwritten if component details or inputs/outputs change.\nCOMPONENT_INFO = {\n    \"inputs\": {\n        \"data\": {\"data_type\": \"ANY\"},\n    },\n    \"outputs\": {\n        \"average\": {\"data_type\": \"ANY\"},\n    },\n    \"name\": \"Average\",\n    \"category\": \"Statistic\",\n    \"description\": \"Calculates the average\",\n    \"version_tag\": \"1.0.0\",\n    \"id\": \"bbf3e562-439a-9662-616f-969bf79d57a2\",\n    \"revision_group_id\": \"bbf3e562-439a-9662-616f-969bf79d57a2\",\n    \"state\": \"RELEASED\",\n    \"released_timestamp\": \"2022-02-09T17:33:33.301070+00:00\",\n}\n\nfrom hdutils import parse_default_value  # noqa: E402, F401\n\n\ndef main(*, data):\n    # entrypoint function for this component\n    # ***** DO NOT EDIT LINES ABOVE *****\n    # write your function code here.\n\n    return {\"average\": data.mean()}\n\n\nTEST_WIRING_FROM_PY_FILE_IMPORT = {}\nRELEASE_WIRING = {}\n",
  "description": "Calculates the average",
  "documentation": "# Average\n\n## Description\nThis component calculates the average of the input.\n\n## Inputs\n* **data** (Pandas Series or Pandas DataFrame): Entries must be numeric.\n\n## Outputs\n* **average** (Float or Pandas Series): The average of **data**. \n\n## Details\nThe component calculates the average of the columns of **data**, excluding NaN respectively None values. \n\nColumns including non-numeric values are ignored. \n\n## Examples\nThe json input of a typical call of this component with a Pandas Series is\n```\n{\n\t\"data\": {\n\t\t\t\t\"2019-08-01T15:20:10\": 1.7,\n\t\t\t\t\"2019-08-01T15:20:20\": null,\n\t\t\t\t\"2019-08-01T15:20:25\": 0.3,\n\t\t\t\t\"2019-08-01T15:20:30\": 1.0\n\t}\n}\n```\nThe expected output is\n```\n\t\"average\": 1 \n```\nThe json input of a typical call of this component with a Pandas DataFrame is\n```\n{\n\t\"data\": {\n\t\t\t\t\"a\": {\n                    \"2019-08-01T15:44:12\": 9,\n                    \"2019-08-01T15:20:12\": -4,\n                    \"2019-08-03T16:20:15\": None,\n                    \"2019-08-05T12:00:34\": 1,\n                },\n                \"b\": {\n                    \"2019-08-01T15:44:12\": -1,\n                    \"2019-08-01T15:20:12\": \"test\",\n                    \"2019-08-03T16:20:15\": 0,\n                    \"2019-08-05T12:00:34\": 4,\n                }\n\t}\n}\n```\nThe expected output is\n```\n\t\"average\": {\n\t\t\t\t\"a\": 2\n\t}\n```\n",
  "id": "bbf3e562-439a-9662-616f-969bf79d57a2",
  "io_interface": {
    "inputs": [
      {
        "data_type": "ANY",
        "id": "b2a0c07a-11a5-898a-e5c5-78f39a9d06b0",
        "name": "data",
        "type": "REQUIRED"
      }
    ],
    "outputs": [
      {
        "data_type": "ANY",
        "id": "ad503a44-073e-aa13-5c9a-906d4c3552ed",
        "name": "average"
      }
    ]
  },
  "name": "Average",
  "release_wiring": {
    "dashboard_positionings": [],
    "input_wirings": [],
    "output_wirings": []
  },
  "released_timestamp": "2022-02-09T17:33:33.301070+00:00",
  "revision_group_id": "bbf3e562-439a-9662-616f-969bf79d57a2",
  "state": "RELEASED",
  "test_wiring": {
    "dashboard_positionings": [],
    "input_wirings": [],
    "output_wirings": []
  },
  "type": "COMPONENT",
  "version_tag": "1.0.0"
}