{
  "category": "Statistic",
  "content": "\"\"\"Documentation for Maximum\n\n# Maximum\n\n## Description\nThis component calculates the maximum of the input.\n\n## Inputs\n* **data** (Pandas Series or Pandas DataFrame): Entries must be numeric.\n\n## Outputs\n* **max** (Float or Pandas Series): The maximum of **data**. \n\n## Details\nThis component calculates the maximum of the columns of **data**.\n\nColumns including non-numeric values are ignored. \n\n## Examples\nThe json input of a typical call of this component with a Pandas Series is\n```\n{\n\t\"data\": {\n\t\t\t\t\"2019-08-01T15:20:10\": 1.7,\n\t\t\t\t\"2019-08-01T15:20:20\": null,\n\t\t\t\t\"2019-08-01T15:20:25\": 0.3,\n\t\t\t\t\"2019-08-01T15:20:30\": 1.0\n\t}\n}\n```\nThe expected output is\n```\n\t\"max\": 1.7 \n```\nThe json input of a typical call of this component with a Pandas DataFrame is\n```\n{\n\t\"data\": {\n\t\t\t\t\"a\": {\n                    \"2019-08-01T15:44:12\": 9,\n                    \"2019-08-01T15:20:12\": -4,\n                    \"2019-08-03T16:20:15\": None,\n                    \"2019-08-05T12:00:34\": 1,\n                },\n                \"b\": {\n                    \"2019-08-01T15:44:12\": -1,\n                    \"2019-08-01T15:20:12\": \"test\",\n                    \"2019-08-03T16:20:15\": 0,\n                    \"2019-08-05T12:00:34\": 4,\n                }\n\t}\n}\n```\nThe expected output is\n```\n\t\"max\": {\n\t\t\t\t\"a\": 9\n\t}\n```\n\"\"\"\n\nimport pandas as pd\n\n# ***** DO NOT EDIT LINES BELOW *****\n# These lines may be overwritten if component details or inputs/outputs change.\nCOMPONENT_INFO = {\n    \"inputs\": {\n        \"data\": {\"data_type\": \"ANY\"},\n    },\n    \"outputs\": {\n        \"max\": {\"data_type\": \"ANY\"},\n    },\n    \"name\": \"Maximum\",\n    \"category\": \"Statistic\",\n    \"description\": \"Calculates the maximum\",\n    \"version_tag\": \"1.0.0\",\n    \"id\": \"d72939c2-1b0c-065e-556a-c9974c179c0f\",\n    \"revision_group_id\": \"d72939c2-1b0c-065e-556a-c9974c179c0f\",\n    \"state\": \"RELEASED\",\n    \"released_timestamp\": \"2022-02-09T17:33:33.646362+00:00\",\n}\n\nfrom hdutils import parse_default_value  # noqa: E402, F401\n\n\ndef main(*, data):\n    # entrypoint function for this component\n    # ***** DO NOT EDIT LINES ABOVE *****\n    # write your function code here.\n\n    return {\"max\": data.max()}\n\n\nTEST_WIRING_FROM_PY_FILE_IMPORT = {}\nRELEASE_WIRING = {}\n",
  "description": "Calculates the maximum",
  "documentation": "# Maximum\n\n## Description\nThis component calculates the maximum of the input.\n\n## Inputs\n* **data** (Pandas Series or Pandas DataFrame): Entries must be numeric.\n\n## Outputs\n* **max** (Float or Pandas Series): The maximum of **data**. \n\n## Details\nThis component calculates the maximum of the columns of **data**.\n\nColumns including non-numeric values are ignored. \n\n## Examples\nThe json input of a typical call of this component with a Pandas Series is\n```\n{\n\t\"data\": {\n\t\t\t\t\"2019-08-01T15:20:10\": 1.7,\n\t\t\t\t\"2019-08-01T15:20:20\": null,\n\t\t\t\t\"2019-08-01T15:20:25\": 0.3,\n\t\t\t\t\"2019-08-01T15:20:30\": 1.0\n\t}\n}\n```\nThe expected output is\n```\n\t\"max\": 1.7 \n```\nThe json input of a typical call of this component with a Pandas DataFrame is\n```\n{\n\t\"data\": {\n\t\t\t\t\"a\": {\n                    \"2019-08-01T15:44:12\": 9,\n                    \"2019-08-01T15:20:12\": -4,\n                    \"2019-08-03T16:20:15\": None,\n                    \"2019-08-05T12:00:34\": 1,\n                },\n                \"b\": {\n                    \"2019-08-01T15:44:12\": -1,\n                    \"2019-08-01T15:20:12\": \"test\",\n                    \"2019-08-03T16:20:15\": 0,\n                    \"2019-08-05T12:00:34\": 4,\n                }\n\t}\n}\n```\nThe expected output is\n```\n\t\"max\": {\n\t\t\t\t\"a\": 9\n\t}\n```\n",
  "id": "d72939c2-1b0c-065e-556a-c9974c179c0f",
  "io_interface": {
    "inputs": [
      {
        "data_type": "ANY",
        "id": "7f421540-fcf7-2467-d3d0-a50a7b363ae8",
        "name": "data",
        "type": "REQUIRED"
      }
    ],
    "outputs": [
      {
        "data_type": "ANY",
        "id": "07cb220c-638b-2d36-4f26-ddbe013e72d8",
        "name": "max"
      }
    ]
  },
  "name": "Maximum",
  "release_wiring": {
    "dashboard_positionings": [],
    "input_wirings": [],
    "output_wirings": []
  },
  "released_timestamp": "2022-02-09T17:33:33.646362+00:00",
  "revision_group_id": "d72939c2-1b0c-065e-556a-c9974c179c0f",
  "state": "RELEASED",
  "test_wiring": {
    "dashboard_positionings": [],
    "input_wirings": [],
    "output_wirings": []
  },
  "type": "COMPONENT",
  "version_tag": "1.0.0"
}