{
  "category": "Statistic",
  "content": "\"\"\"Documentation for Minimum\n\n# Minimum\n\n## Description\nThis component calculates the minimum of the input.\n\n## Inputs\n* **data** (Pandas Series or Pandas DataFrame): Entries must be numeric.\n\n## Outputs\n* **min** (Float or Pandas Series): The minimum of **data**. \n\n## Details\nThis component calculates the minimum of the columns of **data**.\n\nColumns including non-numeric values are ignored. \n\n## Examples\nThe json input of a typical call of this component with a Pandas Series is\n```\n{\n\t\"data\": {\n\t\t\t\t\"2019-08-01T15:20:10\": 1.7,\n\t\t\t\t\"2019-08-01T15:20:20\": null,\n\t\t\t\t\"2019-08-01T15:20:25\": 0.3,\n\t\t\t\t\"2019-08-01T15:20:30\": 1.0\n\t}\n}\n```\nThe expected output is\n```\n\t\"min\": 0.3 \n```\nThe json input of a typical call of this component with a Pandas DataFrame is\n```\n{\n\t\"data\": {\n\t\t\t\t\"a\": {\n                    \"2019-08-01T15:44:12\": 9,\n                    \"2019-08-01T15:20:12\": -4,\n                    \"2019-08-03T16:20:15\": None,\n                    \"2019-08-05T12:00:34\": 1,\n                },\n                \"b\": {\n                    \"2019-08-01T15:44:12\": -1,\n                    \"2019-08-01T15:20:12\": \"test\",\n                    \"2019-08-03T16:20:15\": 0,\n                    \"2019-08-05T12:00:34\": 4,\n                }\n\t}\n}\n```\nThe expected output is\n```\n\t\"min\": {\n\t\t\t\t\"a\": -4\n\t}\n```\n\"\"\"\n\nimport pandas as pd\n\n# ***** DO NOT EDIT LINES BELOW *****\n# These lines may be overwritten if component details or inputs/outputs change.\nCOMPONENT_INFO = {\n    \"inputs\": {\n        \"data\": {\"data_type\": \"ANY\"},\n    },\n    \"outputs\": {\n        \"min\": {\"data_type\": \"ANY\"},\n    },\n    \"name\": \"Minimum\",\n    \"category\": \"Statistic\",\n    \"description\": \"Calculates the minimum\",\n    \"version_tag\": \"1.0.0\",\n    \"id\": \"375819f5-deb3-0d5f-8661-22d202b39c54\",\n    \"revision_group_id\": \"375819f5-deb3-0d5f-8661-22d202b39c54\",\n    \"state\": \"RELEASED\",\n    \"released_timestamp\": \"2022-02-09T17:33:33.382897+00:00\",\n}\n\nfrom hdutils import parse_default_value  # noqa: E402, F401\n\n\ndef main(*, data):\n    # entrypoint function for this component\n    # ***** DO NOT EDIT LINES ABOVE *****\n    # write your function code here.\n\n    return {\"min\": data.min()}\n\n\nTEST_WIRING_FROM_PY_FILE_IMPORT = {}\nRELEASE_WIRING = {}\n",
  "description": "Calculates the minimum",
  "documentation": "# Minimum\n\n## Description\nThis component calculates the minimum of the input.\n\n## Inputs\n* **data** (Pandas Series or Pandas DataFrame): Entries must be numeric.\n\n## Outputs\n* **min** (Float or Pandas Series): The minimum of **data**. \n\n## Details\nThis component calculates the minimum of the columns of **data**.\n\nColumns including non-numeric values are ignored. \n\n## Examples\nThe json input of a typical call of this component with a Pandas Series is\n```\n{\n\t\"data\": {\n\t\t\t\t\"2019-08-01T15:20:10\": 1.7,\n\t\t\t\t\"2019-08-01T15:20:20\": null,\n\t\t\t\t\"2019-08-01T15:20:25\": 0.3,\n\t\t\t\t\"2019-08-01T15:20:30\": 1.0\n\t}\n}\n```\nThe expected output is\n```\n\t\"min\": 0.3 \n```\nThe json input of a typical call of this component with a Pandas DataFrame is\n```\n{\n\t\"data\": {\n\t\t\t\t\"a\": {\n                    \"2019-08-01T15:44:12\": 9,\n                    \"2019-08-01T15:20:12\": -4,\n                    \"2019-08-03T16:20:15\": None,\n                    \"2019-08-05T12:00:34\": 1,\n                },\n                \"b\": {\n                    \"2019-08-01T15:44:12\": -1,\n                    \"2019-08-01T15:20:12\": \"test\",\n                    \"2019-08-03T16:20:15\": 0,\n                    \"2019-08-05T12:00:34\": 4,\n                }\n\t}\n}\n```\nThe expected output is\n```\n\t\"min\": {\n\t\t\t\t\"a\": -4\n\t}\n```\n",
  "id": "375819f5-deb3-0d5f-8661-22d202b39c54",
  "io_interface": {
    "inputs": [
      {
        "data_type": "ANY",
        "id": "5acd4330-5a3b-cfbc-a8f2-c8b9b8eff519",
        "name": "data",
        "type": "REQUIRED"
      }
    ],
    "outputs": [
      {
        "data_type": "ANY",
        "id": "e276294f-3232-2203-5912-b65d8e0a9fd8",
        "name": "min"
      }
    ]
  },
  "name": "Minimum",
  "release_wiring": {
    "dashboard_positionings": [],
    "input_wirings": [],
    "output_wirings": []
  },
  "released_timestamp": "2022-02-09T17:33:33.382897+00:00",
  "revision_group_id": "375819f5-deb3-0d5f-8661-22d202b39c54",
  "state": "RELEASED",
  "test_wiring": {
    "dashboard_positionings": [],
    "input_wirings": [],
    "output_wirings": []
  },
  "type": "COMPONENT",
  "version_tag": "1.0.0"
}