{
  "category": "Statistic",
  "content": "\"\"\"Documentation for Moving minimum number\n\n# Moving minimum number\n\n## Description\nThe component calculates the moving minimum for a constant number of observations.\n\n## Inputs\n* **data** (Pandas Series or Pandas DataFrame): Indices must be numeric or datetimes, entries must be numeric.\n* **n** (Integer): The number of observations, the minimum is calculated for.\n\n## Outputs\n* **movmin** (Pandas Series or Pandas DataFrame): The moving minimum of **data**.\n\n## Details\nThe component calculates the moving minimum for a constant number of observations, sorted by their indices. \n\nTherefore, it excludes NaN respectively None values from **data** and equippes each remaining index with the minimum of the foregoing n numerical observations.   \n\n## Examples\nThe json input of a typical call of this component with a Pandas Series is\n```\n{\n\t\"data\": {\n\t\t\t\t\"2019-08-01T15:20:10\": 3.0,\n\t\t\t\t\"2019-08-01T15:20:20\": null,\n\t\t\t\t\"2019-08-01T15:20:25\": 3.0,\n\t\t\t\t\"2019-08-01T15:20:30\": 0.0,\n\t\t\t\t\"2019-08-01T15:20:35\": 6.0,\n\t\t\t\t\"2019-08-01T15:20:40\": null,\n\t\t\t\t\"2019-08-01T15:20:55\": 12.0,\n\t\t\t\t\"2019-08-01T15:20:56\": 9.0\n\t}, \n\t\"n\": 3\n}\n```\nThe expected output is\n```\n\t\"movmin\": {\n\t\t\t\t\"2019-08-01T15:20:10\": null,\n\t\t\t\t\"2019-08-01T15:20:25\": null,\n\t\t\t\t\"2019-08-01T15:20:30\": 0.0,\n\t\t\t\t\"2019-08-01T15:20:35\": 0.0,\n\t\t\t\t\"2019-08-01T15:20:55\": 0.0,\n\t\t\t\t\"2019-08-01T15:20:56\": 6.0\n\t}\n```\n\"\"\"\n\nimport pandas as pd\nimport numpy as np\n\n# ***** DO NOT EDIT LINES BELOW *****\n# These lines may be overwritten if component details or inputs/outputs change.\nCOMPONENT_INFO = {\n    \"inputs\": {\n        \"data\": {\"data_type\": \"ANY\"},\n        \"n\": {\"data_type\": \"INT\"},\n    },\n    \"outputs\": {\n        \"movmin\": {\"data_type\": \"ANY\"},\n    },\n    \"name\": \"Moving minimum number\",\n    \"category\": \"Statistic\",\n    \"description\": \"Calculates the moving minimum for a constant number of observations\",\n    \"version_tag\": \"1.0.0\",\n    \"id\": \"e79f021a-93a8-d55b-1032-19d91d78fd51\",\n    \"revision_group_id\": \"e79f021a-93a8-d55b-1032-19d91d78fd51\",\n    \"state\": \"RELEASED\",\n    \"released_timestamp\": \"2022-02-09T17:33:33.594171+00:00\",\n}\n\nfrom hdutils import parse_default_value  # noqa: E402, F401\n\n\ndef main(*, data, n):\n    # entrypoint function for this component\n    # ***** DO NOT EDIT LINES ABOVE *****\n    # write your code here.\n\n    data_dropna = data.dropna()\n    if pd.api.types.is_numeric_dtype(data_dropna.index.dtype):\n        data_sort = data_dropna.sort_index()\n\n    else:\n        try:\n            data_dropna.index = pd.to_datetime(data_dropna.index)\n        except (ValueError, TypeError):\n            raise TypeError(\"indices of data must be numeric or datetime\")\n        data_sort = data_dropna.sort_index()\n    return {\"movmin\": data_sort.rolling(n).min()}\n\n\nTEST_WIRING_FROM_PY_FILE_IMPORT = {}\nRELEASE_WIRING = {}\n",
  "description": "Calculates the moving minimum for a constant number of observations",
  "documentation": "# Moving minimum number\n\n## Description\nThe component calculates the moving minimum for a constant number of observations.\n\n## Inputs\n* **data** (Pandas Series or Pandas DataFrame): Indices must be numeric or datetimes, entries must be numeric.\n* **n** (Integer): The number of observations, the minimum is calculated for.\n\n## Outputs\n* **movmin** (Pandas Series or Pandas DataFrame): The moving minimum of **data**.\n\n## Details\nThe component calculates the moving minimum for a constant number of observations, sorted by their indices. \n\nTherefore, it excludes NaN respectively None values from **data** and equippes each remaining index with the minimum of the foregoing n numerical observations.   \n\n## Examples\nThe json input of a typical call of this component with a Pandas Series is\n```\n{\n\t\"data\": {\n\t\t\t\t\"2019-08-01T15:20:10\": 3.0,\n\t\t\t\t\"2019-08-01T15:20:20\": null,\n\t\t\t\t\"2019-08-01T15:20:25\": 3.0,\n\t\t\t\t\"2019-08-01T15:20:30\": 0.0,\n\t\t\t\t\"2019-08-01T15:20:35\": 6.0,\n\t\t\t\t\"2019-08-01T15:20:40\": null,\n\t\t\t\t\"2019-08-01T15:20:55\": 12.0,\n\t\t\t\t\"2019-08-01T15:20:56\": 9.0\n\t}, \n\t\"n\": 3\n}\n```\nThe expected output is\n```\n\t\"movmin\": {\n\t\t\t\t\"2019-08-01T15:20:10\": null,\n\t\t\t\t\"2019-08-01T15:20:25\": null,\n\t\t\t\t\"2019-08-01T15:20:30\": 0.0,\n\t\t\t\t\"2019-08-01T15:20:35\": 0.0,\n\t\t\t\t\"2019-08-01T15:20:55\": 0.0,\n\t\t\t\t\"2019-08-01T15:20:56\": 6.0\n\t}\n```\n",
  "id": "e79f021a-93a8-d55b-1032-19d91d78fd51",
  "io_interface": {
    "inputs": [
      {
        "data_type": "ANY",
        "id": "48a7cb58-647f-d913-47fe-e2f237bc0712",
        "name": "data",
        "type": "REQUIRED"
      },
      {
        "data_type": "INT",
        "id": "f9a58a5b-148b-3d09-7972-5c720fd9b90b",
        "name": "n",
        "type": "REQUIRED"
      }
    ],
    "outputs": [
      {
        "data_type": "ANY",
        "id": "f28696d9-6e6a-1b8f-26f8-33061a551817",
        "name": "movmin"
      }
    ]
  },
  "name": "Moving minimum number",
  "release_wiring": {
    "dashboard_positionings": [],
    "input_wirings": [],
    "output_wirings": []
  },
  "released_timestamp": "2022-02-09T17:33:33.594171+00:00",
  "revision_group_id": "e79f021a-93a8-d55b-1032-19d91d78fd51",
  "state": "RELEASED",
  "test_wiring": {
    "dashboard_positionings": [],
    "input_wirings": [],
    "output_wirings": []
  },
  "type": "COMPONENT",
  "version_tag": "1.0.0"
}