{
  "category": "Statistic",
  "content": "\"\"\"Documentation for Standard deviation\n\n# Standard deviation\n\n## Description\nThis component calculates the standard deviation of the input.\n\n## Inputs\n* **data** (Pandas Series or Pandas DataFrame): Entries must be numeric.\n\n## Outputs\n* **std** (Float or Pandas Series): The standard deviation of **data**. \n\n## Details\nThis component calculates the standard deviation of the columns of **data**, excluding NaN respectively None values. \n\nColumns including non-numeric values are ignored. \n\n## Examples\nThe json input of a typical call of this component with a Pandas Series is\n```\n{\n\t\"data\": {\n\t\t\t\t\"2019-08-01T15:20:10\": 1.7,\n\t\t\t\t\"2019-08-01T15:20:20\": null,\n\t\t\t\t\"2019-08-01T15:20:25\": 0.3,\n\t\t\t\t\"2019-08-01T15:20:30\": 1.0\n\t}\n}\n```\nThe expected output is\n```\n\t\"std\": 0.7 \n```\nThe json input of a typical call of this component with a Pandas DataFrame is\n```\n{\n\t\"data\": {\n\t\t\t\t\"a\": {\n                    \"2019-08-01T15:44:12\": -9,\n                    \"2019-08-01T15:20:12\": 4,\n                    \"2019-08-03T16:20:15\": None,\n                    \"2019-08-05T12:00:34\": 2,\n                },\n                \"b\": {\n                    \"2019-08-01T15:44:12\": -1,\n                    \"2019-08-01T15:20:12\": \"test\",\n                    \"2019-08-03T16:20:15\": 0,\n                    \"2019-08-05T12:00:34\": 4,\n                }\n\t}\n}\n```\nThe expected output is\n```\n\t\"std\": {\n\t\t\t\t\"a\": 7\n\t}\n```\n\"\"\"\n\nimport pandas as pd\n\n# ***** DO NOT EDIT LINES BELOW *****\n# These lines may be overwritten if component details or inputs/outputs change.\nCOMPONENT_INFO = {\n    \"inputs\": {\n        \"data\": {\"data_type\": \"ANY\"},\n    },\n    \"outputs\": {\n        \"std\": {\"data_type\": \"ANY\"},\n    },\n    \"name\": \"Standard deviation\",\n    \"category\": \"Statistic\",\n    \"description\": \"Calculates the standard deviation\",\n    \"version_tag\": \"1.0.0\",\n    \"id\": \"462e4cd5-1772-a925-6d26-8d33011111cd\",\n    \"revision_group_id\": \"462e4cd5-1772-a925-6d26-8d33011111cd\",\n    \"state\": \"RELEASED\",\n    \"released_timestamp\": \"2022-02-09T17:33:33.425137+00:00\",\n}\n\nfrom hdutils import parse_default_value  # noqa: E402, F401\n\n\ndef main(*, data):\n    # entrypoint function for this component\n    # ***** DO NOT EDIT LINES ABOVE *****\n    # write your function code here.\n\n    return {\"std\": data.std()}\n\n\nTEST_WIRING_FROM_PY_FILE_IMPORT = {}\nRELEASE_WIRING = {}\n",
  "description": "Calculates the standard deviation",
  "documentation": "# Standard deviation\n\n## Description\nThis component calculates the standard deviation of the input.\n\n## Inputs\n* **data** (Pandas Series or Pandas DataFrame): Entries must be numeric.\n\n## Outputs\n* **std** (Float or Pandas Series): The standard deviation of **data**. \n\n## Details\nThis component calculates the standard deviation of the columns of **data**, excluding NaN respectively None values. \n\nColumns including non-numeric values are ignored. \n\n## Examples\nThe json input of a typical call of this component with a Pandas Series is\n```\n{\n\t\"data\": {\n\t\t\t\t\"2019-08-01T15:20:10\": 1.7,\n\t\t\t\t\"2019-08-01T15:20:20\": null,\n\t\t\t\t\"2019-08-01T15:20:25\": 0.3,\n\t\t\t\t\"2019-08-01T15:20:30\": 1.0\n\t}\n}\n```\nThe expected output is\n```\n\t\"std\": 0.7 \n```\nThe json input of a typical call of this component with a Pandas DataFrame is\n```\n{\n\t\"data\": {\n\t\t\t\t\"a\": {\n                    \"2019-08-01T15:44:12\": -9,\n                    \"2019-08-01T15:20:12\": 4,\n                    \"2019-08-03T16:20:15\": None,\n                    \"2019-08-05T12:00:34\": 2,\n                },\n                \"b\": {\n                    \"2019-08-01T15:44:12\": -1,\n                    \"2019-08-01T15:20:12\": \"test\",\n                    \"2019-08-03T16:20:15\": 0,\n                    \"2019-08-05T12:00:34\": 4,\n                }\n\t}\n}\n```\nThe expected output is\n```\n\t\"std\": {\n\t\t\t\t\"a\": 7\n\t}\n```\n",
  "id": "462e4cd5-1772-a925-6d26-8d33011111cd",
  "io_interface": {
    "inputs": [
      {
        "data_type": "ANY",
        "id": "c95854a4-8a38-7b84-762c-fc886277d6be",
        "name": "data",
        "type": "REQUIRED"
      }
    ],
    "outputs": [
      {
        "data_type": "ANY",
        "id": "58c23998-b897-2065-ee9a-da65eb72f3ec",
        "name": "std"
      }
    ]
  },
  "name": "Standard deviation",
  "release_wiring": {
    "dashboard_positionings": [],
    "input_wirings": [],
    "output_wirings": []
  },
  "released_timestamp": "2022-02-09T17:33:33.425137+00:00",
  "revision_group_id": "462e4cd5-1772-a925-6d26-8d33011111cd",
  "state": "RELEASED",
  "test_wiring": {
    "dashboard_positionings": [],
    "input_wirings": [],
    "output_wirings": []
  },
  "type": "COMPONENT",
  "version_tag": "1.0.0"
}