{
  "category": "Statistic",
  "content": "from hetdesrun.component.registration import register\n# add your own imports here\n\nimport pandas as pd\nfrom sklearn.preprocessing import StandardScaler\n\n# ***** DO NOT EDIT LINES BELOW *****\n# These lines may be overwritten if component details or inputs/outputs change.\nCOMPONENT_INFO = {\n    \"inputs\": {\n        \"data\": {\"data_type\": \"ANY\"},\n    },\n    \"outputs\": {\n        \"scaled\": {\"data_type\": \"ANY\"},\n    },\n    \"name\": \"Standard Scale\",\n    \"category\": \"Statistic\",\n    \"description\": \"Applies Standard Scaling\",\n    \"version_tag\": \"1.0.0\",\n    \"id\": \"6c4ce4d5-e73f-210e-48a8-230c8e5088ef\",\n    \"revision_group_id\": \"6c4ce4d5-e73f-210e-48a8-230c8e5088ef\",\n    \"state\": \"RELEASED\",\n    \"released_timestamp\": \"2022-02-09T17:33:32.974755+00:00\",\n}\n\nfrom hdutils import parse_default_value  # noqa: E402, F401\n\n\ndef main(*, data):\n    # entrypoint function for this component\n    # ***** DO NOT EDIT LINES ABOVE *****\n    # write your function code here.\n\n    input_data = data if isinstance(data, pd.DataFrame) else data.to_frame()\n\n    scaler = (\n        StandardScaler()\n    )  # Skalierung an Mittelwert und Standard-Abweichung (z-score)\n    scaled = pd.DataFrame(\n        scaler.fit_transform(input_data),\n        columns=input_data.columns,\n        index=input_data.index,\n    )\n\n    return {\"scaled\": scaled if isinstance(data, pd.DataFrame) else scaled.squeeze()}\n\n",
  "description": "Applies Standard Scaling",
  "documentation": "# Standard Scale\n\n## Description\nStandard scaled data.\n\n## Inputs\n* **data** (Pandas Series or Pandas DataFrame): Entries must be numeric.\n\n## Outputs\n* **scaled** (Pandas Series or Pandas DataFrame): The scaled **data**.\n\n## Details\nScales **data** using a standard scaler (i.e. using mean and standard deviation).\n",
  "id": "6c4ce4d5-e73f-210e-48a8-230c8e5088ef",
  "io_interface": {
    "inputs": [
      {
        "data_type": "ANY",
        "id": "e9b15143-fbda-a5da-dbff-566e70e1a596",
        "name": "data",
        "type": "REQUIRED"
      }
    ],
    "outputs": [
      {
        "data_type": "ANY",
        "id": "f663ee05-50a9-fe08-b15a-cb26d845681d",
        "name": "scaled"
      }
    ]
  },
  "name": "Standard Scale",
  "released_timestamp": "2022-02-09T17:33:32.974755+00:00",
  "revision_group_id": "6c4ce4d5-e73f-210e-48a8-230c8e5088ef",
  "state": "RELEASED",
  "test_wiring": {
    "dashboard_positionings": [],
    "input_wirings": [],
    "output_wirings": []
  },
  "type": "COMPONENT",
  "version_tag": "1.0.0"
}