{
  "category": "Basic",
  "content": "\"\"\"Documentation for Filter\n\n# Filter\n\n## Description\nThis component filters a Pandas Series or a Pandas DataFrame by a boolean Pandas Series.\n\n## Inputs\n* **data** (Pandas Series or Pandas DataFrame): The input that should be filtered.\n* **filter_series** (Pandas Series): A Pandas Series with boolean entries.\n\n## Outputs\n* **filtered** (Pandas Series or Pandas DataFrame): The resulting Pandas Series or Pandas DataFrame. \n\n## Details\nThe index of the output contains the indices of data, where filter_series is True. The values of the output are the same as the original ones of data. \n\nNon boolean entries of filter_series are casted to boolean ones in advance to filtering.\n\n## Examples\nThe json input of a typical call of this component with two Pandas Series is\n```\n{\n\t\"data\": {\n\t\t\t\t\"2019-08-01T15:20:12\": 1.2,\n\t\t\t\t\"2019-08-01T15:44:12\": null,\n\t\t\t\t\"2019-08-03T16:20:15\": 0.3,\n\t\t\t\t\"2019-08-05T12:00:34\": 0.5\n\t},\n\t\"filter_series\": {\n\t\t\t\t\"2019-08-01T15:20:12\": true,\n\t\t\t\t\"2019-08-01T15:44:12\": true,\n\t\t\t\t\"2019-08-03T16:20:15\": false,\n\t\t\t\t\"2020-08-05T12:00:34\": true,\n\t\t\t\t\"2020-08-05T12:00:34\": false       \n\t}\n}\n```\nThe expected output is\n```\n\t\"filtered\": {\n\t\t\t\"2019-08-01T15:20:12\": 1.2,\n\t\t\t\"2019-08-01T15:44:12\": null\n\t}\n\n```\n\nThe json input of a typical call of this component with a Pandas DataFrame and a Pandas Series is\n```\n{\n\t\"data\": {\n\t\t\t\"a\": {\n                               \"2019-08-01T15:20:12\": 1.2,\n\t\t\t\t\"2019-08-01T15:44:12\": null,\n\t\t\t\t\"2019-08-03T16:20:15\": 0.3,\n\t\t\t\t\"2019-08-05T12:00:34\": 0.5\n             },\n            \"b\": {\n                                \"2019-08-01T15:20:12\": 54.4,\n\t\t\t\t \"2019-08-01T15:44:12\": 4.3,\n\t\t\t\t \"2019-08-03T16:20:15\": 21.0,\n\t\t\t\t \"2019-08-05T12:00:34\": 7.5\n             }\n\t},\n\t\"filter_series\": {\n\t\t\t\t\"2019-08-01T15:20:12\": true,\n\t\t\t\t\"2019-08-01T15:44:12\": true,\n\t\t\t\t\"2019-08-03T16:20:15\": false,\n\t\t\t\t\"2020-08-05T12:00:34\": true,\n\t\t\t\t\"2020-08-05T12:00:34\": false       \n\t}\n}\n```\nThe expected output is\n```\n\t\"filtered\": {\n\t\t\"a\": {\n\t\t\t\"2019-08-01T15:20:12\": 1.2,\n\t\t\t\"2019-08-01T15:44:12\": null\n\t\t},\n\t\t\"b\": {\n\t\t\t\"2019-08-01T15:20:12\": 54.4,\n\t\t\t\"2019-08-01T15:44:12\": 4.3\n\t\t}\n\t}\n\n```\n\"\"\"\n\nimport pandas as pd\nimport numpy as np\n\n# ***** DO NOT EDIT LINES BELOW *****\n# These lines may be overwritten if component details or inputs/outputs change.\nCOMPONENT_INFO = {\n    \"inputs\": {\n        \"data\": {\"data_type\": \"ANY\"},\n        \"filter_series\": {\"data_type\": \"SERIES\"},\n    },\n    \"outputs\": {\n        \"filtered\": {\"data_type\": \"ANY\"},\n    },\n    \"name\": \"Filter\",\n    \"category\": \"Basic\",\n    \"description\": \"Filters data by filter_series\",\n    \"version_tag\": \"1.0.0\",\n    \"id\": \"18260aab-bdd6-af5c-cac1-7bafde85188f\",\n    \"revision_group_id\": \"18260aab-bdd6-af5c-cac1-7bafde85188f\",\n    \"state\": \"RELEASED\",\n    \"released_timestamp\": \"2022-02-09T17:33:28.399056+00:00\",\n}\n\nfrom hdutils import parse_default_value  # noqa: E402, F401\n\n\ndef main(*, data, filter_series):\n    # entrypoint function for this component\n    # ***** DO NOT EDIT LINES ABOVE *****\n    # write your function code here.\n\n    filter_bool = filter_series.astype(\"bool\")\n    return {\"filtered\": data[filter_bool.reindex(data.index, fill_value=False)]}\n\n\nTEST_WIRING_FROM_PY_FILE_IMPORT = {}\nRELEASE_WIRING = {}\n",
  "description": "Filters data by filter_series",
  "documentation": "# Filter\n\n## Description\nThis component filters a Pandas Series or a Pandas DataFrame by a boolean Pandas Series.\n\n## Inputs\n* **data** (Pandas Series or Pandas DataFrame): The input that should be filtered.\n* **filter_series** (Pandas Series): A Pandas Series with boolean entries.\n\n## Outputs\n* **filtered** (Pandas Series or Pandas DataFrame): The resulting Pandas Series or Pandas DataFrame. \n\n## Details\nThe index of the output contains the indices of data, where filter_series is True. The values of the output are the same as the original ones of data. \n\nNon boolean entries of filter_series are casted to boolean ones in advance to filtering.\n\n## Examples\nThe json input of a typical call of this component with two Pandas Series is\n```\n{\n\t\"data\": {\n\t\t\t\t\"2019-08-01T15:20:12\": 1.2,\n\t\t\t\t\"2019-08-01T15:44:12\": null,\n\t\t\t\t\"2019-08-03T16:20:15\": 0.3,\n\t\t\t\t\"2019-08-05T12:00:34\": 0.5\n\t},\n\t\"filter_series\": {\n\t\t\t\t\"2019-08-01T15:20:12\": true,\n\t\t\t\t\"2019-08-01T15:44:12\": true,\n\t\t\t\t\"2019-08-03T16:20:15\": false,\n\t\t\t\t\"2020-08-05T12:00:34\": true,\n\t\t\t\t\"2020-08-05T12:00:34\": false       \n\t}\n}\n```\nThe expected output is\n```\n\t\"filtered\": {\n\t\t\t\"2019-08-01T15:20:12\": 1.2,\n\t\t\t\"2019-08-01T15:44:12\": null\n\t}\n\n```\n\nThe json input of a typical call of this component with a Pandas DataFrame and a Pandas Series is\n```\n{\n\t\"data\": {\n\t\t\t\"a\": {\n                               \"2019-08-01T15:20:12\": 1.2,\n\t\t\t\t\"2019-08-01T15:44:12\": null,\n\t\t\t\t\"2019-08-03T16:20:15\": 0.3,\n\t\t\t\t\"2019-08-05T12:00:34\": 0.5\n             },\n            \"b\": {\n                                \"2019-08-01T15:20:12\": 54.4,\n\t\t\t\t \"2019-08-01T15:44:12\": 4.3,\n\t\t\t\t \"2019-08-03T16:20:15\": 21.0,\n\t\t\t\t \"2019-08-05T12:00:34\": 7.5\n             }\n\t},\n\t\"filter_series\": {\n\t\t\t\t\"2019-08-01T15:20:12\": true,\n\t\t\t\t\"2019-08-01T15:44:12\": true,\n\t\t\t\t\"2019-08-03T16:20:15\": false,\n\t\t\t\t\"2020-08-05T12:00:34\": true,\n\t\t\t\t\"2020-08-05T12:00:34\": false       \n\t}\n}\n```\nThe expected output is\n```\n\t\"filtered\": {\n\t\t\"a\": {\n\t\t\t\"2019-08-01T15:20:12\": 1.2,\n\t\t\t\"2019-08-01T15:44:12\": null\n\t\t},\n\t\t\"b\": {\n\t\t\t\"2019-08-01T15:20:12\": 54.4,\n\t\t\t\"2019-08-01T15:44:12\": 4.3\n\t\t}\n\t}\n\n```\n\n",
  "id": "18260aab-bdd6-af5c-cac1-7bafde85188f",
  "io_interface": {
    "inputs": [
      {
        "data_type": "ANY",
        "id": "ad0fb04c-fa46-f59d-5d59-054e6fc7b766",
        "name": "data",
        "type": "REQUIRED"
      },
      {
        "data_type": "SERIES",
        "id": "c84b0db5-bbe6-c5ef-a30d-79015134c4cf",
        "name": "filter_series",
        "type": "REQUIRED"
      }
    ],
    "outputs": [
      {
        "data_type": "ANY",
        "id": "4309e6d9-dc4d-781c-4ef4-e2d8fa1d195c",
        "name": "filtered"
      }
    ]
  },
  "name": "Filter",
  "release_wiring": {
    "dashboard_positionings": [],
    "input_wirings": [],
    "output_wirings": []
  },
  "released_timestamp": "2022-02-09T17:33:28.399056+00:00",
  "revision_group_id": "18260aab-bdd6-af5c-cac1-7bafde85188f",
  "state": "RELEASED",
  "test_wiring": {
    "dashboard_positionings": [],
    "input_wirings": [],
    "output_wirings": []
  },
  "type": "COMPONENT",
  "version_tag": "1.0.0"
}