{
  "category": "Basic",
  "content": "\"\"\"Documentation for Greater\n\n# Greater\n\n## Description\nThis component checks if left is greater than right.\n\n## Inputs\n* **left** (Integer, Float, Boolean, Pandas Series or Pandas DataFrame): Entries must be numeric. \n* **right** (Integer, Float, Boolean, Pandas Series or Pandas DataFrame): Entries must be numeric.\n\n## Outputs\n* **result** (Boolean, Pandas Series or Pandas DataFrame): The boolean result of the comparison.\n\n## Details\nThe component checks if left is greater than right.\n\n## Examples\nThe json input of a typical call of this component where left is a Pandas Series and right is numeric is\n```\n{\n\t\"left\": {\n\t\t\t\t\"2019-08-01T15:20:12\": 1.2,\n\t\t\t\t\"2019-08-01T15:44:12\": null,\n\t\t\t\t\"2019-08-03T16:20:15\": 0.3,\n\t\t\t\t\"2019-08-05T12:00:34\": 0.5\n\t},\n\t\"right\": 1\n}\n```\nThe expected output is\n```\n\t\"result\": {\n\t\t\"2019-08-01T15:20:12\": true,\n\t\t\"2019-08-01T15:44:12\": false,\n\t\t\"2019-08-03T16:20:15\": false,\n\t\t\"2019-08-05T12:00:34\": false\n\t}\n```\n\nThe json input of a typical call of this component where left is a Pandas DataFrame and right is numeric is\n```\n{\n\t\"left\": {\n\t\t\t\"a\": {\n                               \"2019-08-01T15:20:12\": 1.2,\n\t\t\t\t\"2019-08-01T15:44:12\": null,\n\t\t\t\t\"2019-08-03T16:20:15\": 0.3,\n\t\t\t\t\"2019-08-05T12:00:34\": 0.5\n             },\n            \"b\": {\n                                \"2019-08-01T15:20:12\": 54.4,\n\t\t\t\t \"2019-08-01T15:44:12\": 4.3,\n\t\t\t\t \"2019-08-03T16:20:15\": 21.0,\n\t\t\t\t \"2019-08-05T12:00:34\": 7.5\n             }\n\t},\n\t\"right\": 0.8\n}\n```\nThe expected output is\n```\n\t\"result\": {\n\t\t\t\"a\": {\n\t\t\t\t\"2019-08-01T15:20:12\": true,\n\t\t\t\t\"2019-08-01T15:44:12\": false,\n\t\t\t\t\"2019-08-03T16:20:15\": false,\n\t\t\t\t\"2019-08-05T12:00:34\": false\n\t\t\t},\n\t\t\t\"b\": {\n\t\t\t\t\"2019-08-01T15:20:12\": true,\n\t\t\t\t\"2019-08-01T15:44:12\": true,\n\t\t\t\t\"2019-08-03T16:20:15\": true,\n\t\t\t\t\"2019-08-05T12:00:34\": true\n\t\t\t}\n\t\t}\n\n\n```\n\nThe json input of a typical call of this component where both left and right are Pandas Series is\n```\n{\n\t\"left\": {\n\t\t\t\t\"2019-08-01T15:20:12\": 1.2,\n\t\t\t\t\"2019-08-01T15:44:12\": null,\n\t\t\t\t\"2019-08-03T16:20:15\": 0.3,\n\t\t\t\t\"2019-08-05T12:00:34\": 0.5\n\t},\n\t\"right\": {\n\t\t\t\t\"2019-08-01T15:20:12\": 1.0,\n\t\t\t\t\"2019-08-01T15:44:12\": 27,\n\t\t\t\t\"2019-08-03T16:20:15\": 3.6,\n\t\t\t\t\"2020-08-05T12:00:34\": 17,\n\t\t\t\t\"2021-08-05T12:00:34\": null       \n\t}\n}\n```\nThe expected output is\n```\n\t\"result\": {\n\t\t\t\"2019-08-01T15:20:12\": true,\n\t\t\t\"2019-08-01T15:44:12\": false,\n\t\t\t\"2019-08-03T16:20:15\": false,\n\t\t\t\"2019-08-05T12:00:34\": false,\n\t\t\t\"2020-08-05T12:00:34\": false,\n\t\t\t\"2021-08-05T12:00:34\": false\n\t\t}\n```\n\"\"\"\n\nimport pandas as pd\n\n# ***** DO NOT EDIT LINES BELOW *****\n# These lines may be overwritten if component details or inputs/outputs change.\nCOMPONENT_INFO = {\n    \"inputs\": {\n        \"left\": {\"data_type\": \"ANY\"},\n        \"right\": {\"data_type\": \"ANY\"},\n    },\n    \"outputs\": {\n        \"result\": {\"data_type\": \"ANY\"},\n    },\n    \"name\": \"Greater\",\n    \"category\": \"Basic\",\n    \"description\": \"Checks if left is greater than right\",\n    \"version_tag\": \"1.0.0\",\n    \"id\": \"e6918e9e-aaaf-6f84-175a-fc2ac03ed85d\",\n    \"revision_group_id\": \"e6918e9e-aaaf-6f84-175a-fc2ac03ed85d\",\n    \"state\": \"RELEASED\",\n    \"released_timestamp\": \"2022-02-09T17:33:28.221351+00:00\",\n}\n\nfrom hdutils import parse_default_value  # noqa: E402, F401\n\n\ndef main(*, left, right):\n    # entrypoint function for this component\n    # ***** DO NOT EDIT LINES ABOVE *****\n    # write your function code here.\n\n    try:\n        return {\"result\": left > right}\n    except ValueError:\n        return {\"result\": left.gt(right)}\n\n\nTEST_WIRING_FROM_PY_FILE_IMPORT = {}\nRELEASE_WIRING = {}\n",
  "description": "Checks if left is greater than right",
  "documentation": "# Greater\n\n## Description\nThis component checks if left is greater than right.\n\n## Inputs\n* **left** (Integer, Float, Boolean, Pandas Series or Pandas DataFrame): Entries must be numeric. \n* **right** (Integer, Float, Boolean, Pandas Series or Pandas DataFrame): Entries must be numeric.\n\n## Outputs\n* **result** (Boolean, Pandas Series or Pandas DataFrame): The boolean result of the comparison.\n\n## Details\nThe component checks if left is greater than right.\n\n## Examples\nThe json input of a typical call of this component where left is a Pandas Series and right is numeric is\n```\n{\n\t\"left\": {\n\t\t\t\t\"2019-08-01T15:20:12\": 1.2,\n\t\t\t\t\"2019-08-01T15:44:12\": null,\n\t\t\t\t\"2019-08-03T16:20:15\": 0.3,\n\t\t\t\t\"2019-08-05T12:00:34\": 0.5\n\t},\n\t\"right\": 1\n}\n```\nThe expected output is\n```\n\t\"result\": {\n\t\t\"2019-08-01T15:20:12\": true,\n\t\t\"2019-08-01T15:44:12\": false,\n\t\t\"2019-08-03T16:20:15\": false,\n\t\t\"2019-08-05T12:00:34\": false\n\t}\n```\n\nThe json input of a typical call of this component where left is a Pandas DataFrame and right is numeric is\n```\n{\n\t\"left\": {\n\t\t\t\"a\": {\n                               \"2019-08-01T15:20:12\": 1.2,\n\t\t\t\t\"2019-08-01T15:44:12\": null,\n\t\t\t\t\"2019-08-03T16:20:15\": 0.3,\n\t\t\t\t\"2019-08-05T12:00:34\": 0.5\n             },\n            \"b\": {\n                                \"2019-08-01T15:20:12\": 54.4,\n\t\t\t\t \"2019-08-01T15:44:12\": 4.3,\n\t\t\t\t \"2019-08-03T16:20:15\": 21.0,\n\t\t\t\t \"2019-08-05T12:00:34\": 7.5\n             }\n\t},\n\t\"right\": 0.8\n}\n```\nThe expected output is\n```\n\t\"result\": {\n\t\t\t\"a\": {\n\t\t\t\t\"2019-08-01T15:20:12\": true,\n\t\t\t\t\"2019-08-01T15:44:12\": false,\n\t\t\t\t\"2019-08-03T16:20:15\": false,\n\t\t\t\t\"2019-08-05T12:00:34\": false\n\t\t\t},\n\t\t\t\"b\": {\n\t\t\t\t\"2019-08-01T15:20:12\": true,\n\t\t\t\t\"2019-08-01T15:44:12\": true,\n\t\t\t\t\"2019-08-03T16:20:15\": true,\n\t\t\t\t\"2019-08-05T12:00:34\": true\n\t\t\t}\n\t\t}\n\n\n```\n\nThe json input of a typical call of this component where both left and right are Pandas Series is\n```\n{\n\t\"left\": {\n\t\t\t\t\"2019-08-01T15:20:12\": 1.2,\n\t\t\t\t\"2019-08-01T15:44:12\": null,\n\t\t\t\t\"2019-08-03T16:20:15\": 0.3,\n\t\t\t\t\"2019-08-05T12:00:34\": 0.5\n\t},\n\t\"right\": {\n\t\t\t\t\"2019-08-01T15:20:12\": 1.0,\n\t\t\t\t\"2019-08-01T15:44:12\": 27,\n\t\t\t\t\"2019-08-03T16:20:15\": 3.6,\n\t\t\t\t\"2020-08-05T12:00:34\": 17,\n\t\t\t\t\"2021-08-05T12:00:34\": null       \n\t}\n}\n```\nThe expected output is\n```\n\t\"result\": {\n\t\t\t\"2019-08-01T15:20:12\": true,\n\t\t\t\"2019-08-01T15:44:12\": false,\n\t\t\t\"2019-08-03T16:20:15\": false,\n\t\t\t\"2019-08-05T12:00:34\": false,\n\t\t\t\"2020-08-05T12:00:34\": false,\n\t\t\t\"2021-08-05T12:00:34\": false\n\t\t}\n```\n",
  "id": "e6918e9e-aaaf-6f84-175a-fc2ac03ed85d",
  "io_interface": {
    "inputs": [
      {
        "data_type": "ANY",
        "id": "791d799b-e78f-53ce-b1e0-0f79ff260269",
        "name": "left",
        "type": "REQUIRED"
      },
      {
        "data_type": "ANY",
        "id": "1422edfb-fa9c-a3cf-b846-9735f47a9ce7",
        "name": "right",
        "type": "REQUIRED"
      }
    ],
    "outputs": [
      {
        "data_type": "ANY",
        "id": "3446dce1-6305-f454-ee2c-81b68aa33388",
        "name": "result"
      }
    ]
  },
  "name": "Greater",
  "release_wiring": {
    "dashboard_positionings": [],
    "input_wirings": [],
    "output_wirings": []
  },
  "released_timestamp": "2022-02-09T17:33:28.221351+00:00",
  "revision_group_id": "e6918e9e-aaaf-6f84-175a-fc2ac03ed85d",
  "state": "RELEASED",
  "test_wiring": {
    "dashboard_positionings": [],
    "input_wirings": [],
    "output_wirings": []
  },
  "type": "COMPONENT",
  "version_tag": "1.0.0"
}