{
  "category": "Basic",
  "content": "\"\"\"Documentation for Inequality\n\n# Inequality\n\n## Description\nThis component checks if left is unequal to right.\n\n## Inputs\n* **left** (Integer, Float, Boolean, Pandas Series or Pandas DataFrame): Entries must be numeric. \n* **right** (Integer, Float, Boolean, Pandas Series or Pandas DataFrame): Entries must be numeric.\n\n## Outputs\n* **result** (Boolean, Pandas Series or Pandas DataFrame): The boolean result of the comparison.\n\n## Details\nThe component checks if left is unequal to right.\n\n## Examples\nThe json input of a typical call of this component where left is a Pandas Series and right is numeric is\n```\n{\n\t\"left\": {\n\t\t\t\t\"2019-08-01T15:20:12\": 1.2,\n\t\t\t\t\"2019-08-01T15:44:12\": null,\n\t\t\t\t\"2019-08-03T16:20:15\": 0.3,\n\t\t\t\t\"2019-08-05T12:00:34\": 0.5\n\t},\n\t\"right\": 0.5\n}\n```\nThe expected output is\n```\n\t\"result\": {\n\t\t\"2019-08-01T15:20:12\": true,\n\t\t\"2019-08-01T15:44:12\": false,\n\t\t\"2019-08-03T16:20:15\": true,\n\t\t\"2019-08-05T12:00:34\": false\n\t}\n```\n\nThe json input of a typical call of this component where left is a Pandas DataFrame and right is numeric is\n```\n{\n\t\"left\": {\n\t\t\t\"a\": {\n                               \"2019-08-01T15:20:12\": 1.2,\n\t\t\t\t\"2019-08-01T15:44:12\": null,\n\t\t\t\t\"2019-08-03T16:20:15\": 0.3,\n\t\t\t\t\"2019-08-05T12:00:34\": 0.5\n             },\n            \"b\": {\n                                \"2019-08-01T15:20:12\": 54.4,\n\t\t\t\t \"2019-08-01T15:44:12\": 0.5,\n\t\t\t\t \"2019-08-03T16:20:15\": 21.0,\n\t\t\t\t \"2019-08-05T12:00:34\": 7.5\n             }\n\t},\n\t\"right\": 0.5\n}\n```\nThe expected output is\n```\n\t\"result\": {\n\t\t\t\"a\": {\n\t\t\t\t\"2019-08-01T15:20:12\": true,\n\t\t\t\t\"2019-08-01T15:44:12\": false,\n\t\t\t\t\"2019-08-03T16:20:15\": true,\n\t\t\t\t\"2019-08-05T12:00:34\": false\n\t\t\t},\n\t\t\t\"b\": {\n\t\t\t\t\"2019-08-01T15:20:12\": true,\n\t\t\t\t\"2019-08-01T15:44:12\": false,\n\t\t\t\t\"2019-08-03T16:20:15\": true,\n\t\t\t\t\"2019-08-05T12:00:34\": true\n\t\t\t}\n\t\t}\n\n\n```\n\nThe json input of a typical call of this component where both left and right are Pandas Series is\n```\n{\n\t\"left\": {\n\t\t\t\t\"2019-08-01T15:20:12\": 1.2,\n\t\t\t\t\"2019-08-01T15:44:12\": null,\n\t\t\t\t\"2019-08-03T16:20:15\": 0.3,\n\t\t\t\t\"2019-08-05T12:00:34\": 0.5\n\t},\n\t\"right\": {\n\t\t\t\t\"2019-08-01T15:20:12\": 1.0,\n\t\t\t\t\"2019-08-01T15:44:12\": 27,\n\t\t\t\t\"2019-08-03T16:20:15\": 0.5,\n\t\t\t\t\"2020-08-05T12:00:34\": 17,\n\t\t\t\t\"2021-08-05T12:00:34\": null       \n\t}\n}\n```\nThe expected output is\n```\n\t\"result\": {\n\t\t\t\"2019-08-01T15:20:12\": true,\n\t\t\t\"2019-08-01T15:44:12\": false,\n\t\t\t\"2019-08-03T16:20:15\": true,\n\t\t\t\"2019-08-05T12:00:34\": false,\n\t\t\t\"2020-08-05T12:00:34\": false,\n\t\t\t\"2021-08-05T12:00:34\": false\n\t\t}\n```\n\"\"\"\n\nimport pandas as pd\n\n# ***** DO NOT EDIT LINES BELOW *****\n# These lines may be overwritten if component details or inputs/outputs change.\nCOMPONENT_INFO = {\n    \"inputs\": {\n        \"left\": {\"data_type\": \"ANY\"},\n        \"right\": {\"data_type\": \"ANY\"},\n    },\n    \"outputs\": {\n        \"result\": {\"data_type\": \"ANY\"},\n    },\n    \"name\": \"Inequality\",\n    \"category\": \"Basic\",\n    \"description\": \"Checks if left is unequal to right\",\n    \"version_tag\": \"1.0.0\",\n    \"id\": \"4ec3ef23-6bea-872d-1905-c9c6d06dddef\",\n    \"revision_group_id\": \"4ec3ef23-6bea-872d-1905-c9c6d06dddef\",\n    \"state\": \"RELEASED\",\n    \"released_timestamp\": \"2022-02-09T17:33:28.687616+00:00\",\n}\n\nfrom hdutils import parse_default_value  # noqa: E402, F401\n\n\ndef main(*, left, right):\n    # entrypoint function for this component\n    # ***** DO NOT EDIT LINES ABOVE *****\n    # write your function code here.\n\n    try:\n        return {\"result\": left != right}\n    except ValueError:\n        return {\"result\": left.ne(right)}\n\n\nTEST_WIRING_FROM_PY_FILE_IMPORT = {}\n",
  "description": "Checks if left is unequal to right",
  "documentation": "# Inequality\n\n## Description\nThis component checks if left is unequal to right.\n\n## Inputs\n* **left** (Integer, Float, Boolean, Pandas Series or Pandas DataFrame): Entries must be numeric. \n* **right** (Integer, Float, Boolean, Pandas Series or Pandas DataFrame): Entries must be numeric.\n\n## Outputs\n* **result** (Boolean, Pandas Series or Pandas DataFrame): The boolean result of the comparison.\n\n## Details\nThe component checks if left is unequal to right.\n\n## Examples\nThe json input of a typical call of this component where left is a Pandas Series and right is numeric is\n```\n{\n\t\"left\": {\n\t\t\t\t\"2019-08-01T15:20:12\": 1.2,\n\t\t\t\t\"2019-08-01T15:44:12\": null,\n\t\t\t\t\"2019-08-03T16:20:15\": 0.3,\n\t\t\t\t\"2019-08-05T12:00:34\": 0.5\n\t},\n\t\"right\": 0.5\n}\n```\nThe expected output is\n```\n\t\"result\": {\n\t\t\"2019-08-01T15:20:12\": true,\n\t\t\"2019-08-01T15:44:12\": false,\n\t\t\"2019-08-03T16:20:15\": true,\n\t\t\"2019-08-05T12:00:34\": false\n\t}\n```\n\nThe json input of a typical call of this component where left is a Pandas DataFrame and right is numeric is\n```\n{\n\t\"left\": {\n\t\t\t\"a\": {\n                               \"2019-08-01T15:20:12\": 1.2,\n\t\t\t\t\"2019-08-01T15:44:12\": null,\n\t\t\t\t\"2019-08-03T16:20:15\": 0.3,\n\t\t\t\t\"2019-08-05T12:00:34\": 0.5\n             },\n            \"b\": {\n                                \"2019-08-01T15:20:12\": 54.4,\n\t\t\t\t \"2019-08-01T15:44:12\": 0.5,\n\t\t\t\t \"2019-08-03T16:20:15\": 21.0,\n\t\t\t\t \"2019-08-05T12:00:34\": 7.5\n             }\n\t},\n\t\"right\": 0.5\n}\n```\nThe expected output is\n```\n\t\"result\": {\n\t\t\t\"a\": {\n\t\t\t\t\"2019-08-01T15:20:12\": true,\n\t\t\t\t\"2019-08-01T15:44:12\": false,\n\t\t\t\t\"2019-08-03T16:20:15\": true,\n\t\t\t\t\"2019-08-05T12:00:34\": false\n\t\t\t},\n\t\t\t\"b\": {\n\t\t\t\t\"2019-08-01T15:20:12\": true,\n\t\t\t\t\"2019-08-01T15:44:12\": false,\n\t\t\t\t\"2019-08-03T16:20:15\": true,\n\t\t\t\t\"2019-08-05T12:00:34\": true\n\t\t\t}\n\t\t}\n\n\n```\n\nThe json input of a typical call of this component where both left and right are Pandas Series is\n```\n{\n\t\"left\": {\n\t\t\t\t\"2019-08-01T15:20:12\": 1.2,\n\t\t\t\t\"2019-08-01T15:44:12\": null,\n\t\t\t\t\"2019-08-03T16:20:15\": 0.3,\n\t\t\t\t\"2019-08-05T12:00:34\": 0.5\n\t},\n\t\"right\": {\n\t\t\t\t\"2019-08-01T15:20:12\": 1.0,\n\t\t\t\t\"2019-08-01T15:44:12\": 27,\n\t\t\t\t\"2019-08-03T16:20:15\": 0.5,\n\t\t\t\t\"2020-08-05T12:00:34\": 17,\n\t\t\t\t\"2021-08-05T12:00:34\": null       \n\t}\n}\n```\nThe expected output is\n```\n\t\"result\": {\n\t\t\t\"2019-08-01T15:20:12\": true,\n\t\t\t\"2019-08-01T15:44:12\": false,\n\t\t\t\"2019-08-03T16:20:15\": true,\n\t\t\t\"2019-08-05T12:00:34\": false,\n\t\t\t\"2020-08-05T12:00:34\": false,\n\t\t\t\"2021-08-05T12:00:34\": false\n\t\t}\n```\n",
  "id": "4ec3ef23-6bea-872d-1905-c9c6d06dddef",
  "io_interface": {
    "inputs": [
      {
        "data_type": "ANY",
        "id": "4b0b61ae-d560-6687-7c97-fdd15d9798d8",
        "name": "left",
        "type": "REQUIRED"
      },
      {
        "data_type": "ANY",
        "id": "3f8bcc87-a39f-7f4c-0943-e3efcd9b01f0",
        "name": "right",
        "type": "REQUIRED"
      }
    ],
    "outputs": [
      {
        "data_type": "ANY",
        "id": "3f28c477-9d86-a82c-885b-4e8f2f967fb3",
        "name": "result"
      }
    ]
  },
  "name": "Inequality",
  "released_timestamp": "2022-02-09T17:33:28.687616+00:00",
  "revision_group_id": "4ec3ef23-6bea-872d-1905-c9c6d06dddef",
  "state": "RELEASED",
  "test_wiring": {
    "dashboard_positionings": [],
    "input_wirings": [],
    "output_wirings": []
  },
  "type": "COMPONENT",
  "version_tag": "1.0.0"
}