{
  "category": "Basic Arithmetic",
  "content": "\"\"\"Documentation for Abs\n\n# Abs\n\n## Description\nThis component calculates the absolute value of the input.\n\n## Inputs\n* **data** (Integer, Float, Pandas Series or Pandas DataFrame): Entries must be numeric.\n\n## Outputs\n* **absolute** (Integer, Float, Pandas Series or Pandas DataFrame): Absolute value of data.\n\n## Details\nThe component calculates the absolute value of the input. \n\n## Examples\nThe json input of a typical call of this component with a Pandas Series is\n```\n{\n\t\"data\": {\n\t\t\t\t\"2019-08-01T15:20:12\": 4,\n\t\t\t\t\"2019-08-01T15:44:12\": -9,\n\t\t\t\t\"2019-08-03T16:20:15\": 0,\n\t\t\t\t\"2019-08-05T12:00:34\": null,\n                               \"2019-08-07T11:01:00\": -100\n\t}\n}\n```\nThe expected output is\n```\n\t\"absolute\": {\n\t\t\t\t\"2019-08-01T15:20:12\": 4,\n\t\t\t\t\"2019-08-01T15:44:12\": 9,\n\t\t\t\t\"2019-08-03T16:20:15\": 0,\n\t\t\t\t\"2019-08-05T12:00:34\": null,\n                               \"2019-08-07T11:01:00\": 100\n\t}\n\n```\n\"\"\"\n\nimport pandas as pd\nimport numpy as np\n\n# ***** DO NOT EDIT LINES BELOW *****\n# These lines may be overwritten if component details or inputs/outputs change.\nCOMPONENT_INFO = {\n    \"inputs\": {\n        \"data\": {\"data_type\": \"ANY\"},\n    },\n    \"outputs\": {\n        \"absolute\": {\"data_type\": \"ANY\"},\n    },\n    \"name\": \"Abs\",\n    \"category\": \"Basic Arithmetic\",\n    \"description\": \"Returns absolute values\",\n    \"version_tag\": \"1.0.0\",\n    \"id\": \"ea4a196f-5d94-d3cf-02e8-8c750414fc89\",\n    \"revision_group_id\": \"ea4a196f-5d94-d3cf-02e8-8c750414fc89\",\n    \"state\": \"RELEASED\",\n    \"released_timestamp\": \"2022-02-09T17:33:32.270360+00:00\",\n}\n\nfrom hdutils import parse_default_value  # noqa: E402, F401\n\n\ndef main(*, data):\n    # entrypoint function for this component\n    # ***** DO NOT EDIT LINES ABOVE *****\n    # write your function code here.\n\n    return {\"absolute\": abs(data)}\n\n\nTEST_WIRING_FROM_PY_FILE_IMPORT = {}\nRELEASE_WIRING = {}\n",
  "description": "Returns absolute values",
  "documentation": "# Abs\n\n## Description\nThis component calculates the absolute value of the input.\n\n## Inputs\n* **data** (Integer, Float, Pandas Series or Pandas DataFrame): Entries must be numeric.\n\n## Outputs\n* **absolute** (Integer, Float, Pandas Series or Pandas DataFrame): Absolute value of data.\n\n## Details\nThe component calculates the absolute value of the input. \n\n## Examples\nThe json input of a typical call of this component with a Pandas Series is\n```\n{\n\t\"data\": {\n\t\t\t\t\"2019-08-01T15:20:12\": 4,\n\t\t\t\t\"2019-08-01T15:44:12\": -9,\n\t\t\t\t\"2019-08-03T16:20:15\": 0,\n\t\t\t\t\"2019-08-05T12:00:34\": null,\n                               \"2019-08-07T11:01:00\": -100\n\t}\n}\n```\nThe expected output is\n```\n\t\"absolute\": {\n\t\t\t\t\"2019-08-01T15:20:12\": 4,\n\t\t\t\t\"2019-08-01T15:44:12\": 9,\n\t\t\t\t\"2019-08-03T16:20:15\": 0,\n\t\t\t\t\"2019-08-05T12:00:34\": null,\n                               \"2019-08-07T11:01:00\": 100\n\t}\n\n```\n",
  "id": "ea4a196f-5d94-d3cf-02e8-8c750414fc89",
  "io_interface": {
    "inputs": [
      {
        "data_type": "ANY",
        "id": "2bf34e30-2de3-b373-e214-b2354eb14d27",
        "name": "data",
        "type": "REQUIRED"
      }
    ],
    "outputs": [
      {
        "data_type": "ANY",
        "id": "4280fb87-b12a-44af-8a9e-250912467d0e",
        "name": "absolute"
      }
    ]
  },
  "name": "Abs",
  "release_wiring": {
    "dashboard_positionings": [],
    "input_wirings": [],
    "output_wirings": []
  },
  "released_timestamp": "2022-02-09T17:33:32.270360+00:00",
  "revision_group_id": "ea4a196f-5d94-d3cf-02e8-8c750414fc89",
  "state": "RELEASED",
  "test_wiring": {
    "dashboard_positionings": [],
    "input_wirings": [],
    "output_wirings": []
  },
  "type": "COMPONENT",
  "version_tag": "1.0.0"
}