{
  "category": "Basic Arithmetic",
  "content": "\"\"\"Documentation for Add\n\n# Add\n\n## Description\nThis component adds numeric values, Pandas Series and Pandas DataFrames.\n\n## Inputs\n* **a** (Integer, Float, Pandas Series or Pandas DataFrame): First summand, entries must be numeric.\n* **b** (Integer, Float, Pandas Series or Pandas DataFrame): Second summand, entries must be numeric.\n\n## Outputs\n* **sum** (Integer, Float, Pandas Series or Pandas DataFrame): The sum of summand a and summand b. \n\n## Details\nThe component adds the inputs. \n\n## Examples\nThe json input of a typical call of this component with two Pandas Series is\n```\n{\n\t\"a\": {\n\t\t\t\t\"2019-08-01T15:20:12\": 1.2,\n\t\t\t\t\"2019-08-01T15:44:12\": 0.0,\n\t\t\t\t\"2019-08-03T16:20:15\": 0.3,\n\t\t\t\t\"2019-08-05T12:00:34\": 0.5,\n                               \"2019-08-07T11:01:00\": 7.8\n\t},\n\t\"b\": {\n\t\t\t\t\"2019-08-01T15:20:12\": 1.4,\n\t\t\t\t\"2019-08-01T15:44:12\": 2.6,\n\t\t\t\t\"2019-08-03T16:20:15\": 3.8,\n\t\t\t\t\"2019-08-05T12:00:34\": 5.0    \n\t}\n}\n```\nThe expected output is\n```\n\t\"sum\": {\n\t\t\t\"2019-08-01T15:20:12\": 3.6,\n\t\t\t\"2019-08-01T15:44:12\": 2.6,\n\t\t\t\"2019-08-03T16:20:15\": 4.1,\n\t\t\t\"2019-08-05T12:00:34\": 5.5,\n                       \"2019-08-07T11:01:00\": null  \n\t}\n```\n\nThe json input of a typical call of this component with a Float and a Pandas DataFrame is\n```\n{\n\t\"a\": 5.1\n        \"b\": {\n\t\t\t\"first\": {\n                               \"2019-08-01T15:20:12\": 1.2,\n\t\t\t\t\"2019-08-01T15:44:12\": null,\n\t\t\t\t\"2019-08-03T16:20:15\": 0.3,\n\t\t\t\t\"2019-08-05T12:00:34\": 0.5\n             },\n            \"second\": {\n                                \"2019-08-01T15:20:12\": 54.4,\n\t\t\t\t \"2019-08-01T15:44:12\": 4.3,\n\t\t\t\t \"2019-08-03T16:20:15\": 21.0,\n\t\t\t\t \"2019-08-05T12:00:34\": 7.5\n             }\n\t}\n}\n```\nThe expected output is\n```\n\t\"sum\": {\n\t\t\t\"first\": {\n                               \"2019-08-01T15:20:12\": 6.3,\n\t\t\t\t\"2019-08-01T15:44:12\": null,\n\t\t\t\t\"2019-08-03T16:20:15\": 5.4,\n\t\t\t\t\"2019-08-05T12:00:34\": 5.6\n             },\n            \"second\": {\n                                \"2019-08-01T15:20:12\": 59.5,\n\t\t\t\t \"2019-08-01T15:44:12\": 9.4,\n\t\t\t\t \"2019-08-03T16:20:15\": 26.1,\n\t\t\t\t \"2019-08-05T12:00:34\": 12.6\n             }\n\t}\n```\n\"\"\"\n\nimport pandas as pd\n\n# ***** DO NOT EDIT LINES BELOW *****\n# These lines may be overwritten if component details or inputs/outputs change.\nCOMPONENT_INFO = {\n    \"inputs\": {\n        \"a\": {\"data_type\": \"ANY\"},\n        \"b\": {\"data_type\": \"ANY\"},\n    },\n    \"outputs\": {\n        \"sum\": {\"data_type\": \"ANY\"},\n    },\n    \"name\": \"Add\",\n    \"category\": \"Basic Arithmetic\",\n    \"description\": \"Add inputs\",\n    \"version_tag\": \"1.0.0\",\n    \"id\": \"2abf72f6-68c9-7398-7175-165d31b3ced7\",\n    \"revision_group_id\": \"2abf72f6-68c9-7398-7175-165d31b3ced7\",\n    \"state\": \"RELEASED\",\n    \"released_timestamp\": \"2022-02-09T17:33:32.478184+00:00\",\n}\n\nfrom hdutils import parse_default_value  # noqa: E402, F401\n\n\ndef main(*, a, b):\n    # entrypoint function for this component\n    # ***** DO NOT EDIT LINES ABOVE *****\n\n    return {\"sum\": (a + b)}\n\n\nTEST_WIRING_FROM_PY_FILE_IMPORT = {}\nRELEASE_WIRING = {}\n",
  "description": "Add inputs",
  "documentation": "# Add\n\n## Description\nThis component adds numeric values, Pandas Series and Pandas DataFrames.\n\n## Inputs\n* **a** (Integer, Float, Pandas Series or Pandas DataFrame): First summand, entries must be numeric.\n* **b** (Integer, Float, Pandas Series or Pandas DataFrame): Second summand, entries must be numeric.\n\n## Outputs\n* **sum** (Integer, Float, Pandas Series or Pandas DataFrame): The sum of summand a and summand b. \n\n## Details\nThe component adds the inputs. \n\n## Examples\nThe json input of a typical call of this component with two Pandas Series is\n```\n{\n\t\"a\": {\n\t\t\t\t\"2019-08-01T15:20:12\": 1.2,\n\t\t\t\t\"2019-08-01T15:44:12\": 0.0,\n\t\t\t\t\"2019-08-03T16:20:15\": 0.3,\n\t\t\t\t\"2019-08-05T12:00:34\": 0.5,\n                               \"2019-08-07T11:01:00\": 7.8\n\t},\n\t\"b\": {\n\t\t\t\t\"2019-08-01T15:20:12\": 1.4,\n\t\t\t\t\"2019-08-01T15:44:12\": 2.6,\n\t\t\t\t\"2019-08-03T16:20:15\": 3.8,\n\t\t\t\t\"2019-08-05T12:00:34\": 5.0    \n\t}\n}\n```\nThe expected output is\n```\n\t\"sum\": {\n\t\t\t\"2019-08-01T15:20:12\": 3.6,\n\t\t\t\"2019-08-01T15:44:12\": 2.6,\n\t\t\t\"2019-08-03T16:20:15\": 4.1,\n\t\t\t\"2019-08-05T12:00:34\": 5.5,\n                       \"2019-08-07T11:01:00\": null  \n\t}\n```\n\nThe json input of a typical call of this component with a Float and a Pandas DataFrame is\n```\n{\n\t\"a\": 5.1\n        \"b\": {\n\t\t\t\"first\": {\n                               \"2019-08-01T15:20:12\": 1.2,\n\t\t\t\t\"2019-08-01T15:44:12\": null,\n\t\t\t\t\"2019-08-03T16:20:15\": 0.3,\n\t\t\t\t\"2019-08-05T12:00:34\": 0.5\n             },\n            \"second\": {\n                                \"2019-08-01T15:20:12\": 54.4,\n\t\t\t\t \"2019-08-01T15:44:12\": 4.3,\n\t\t\t\t \"2019-08-03T16:20:15\": 21.0,\n\t\t\t\t \"2019-08-05T12:00:34\": 7.5\n             }\n\t}\n}\n```\nThe expected output is\n```\n\t\"sum\": {\n\t\t\t\"first\": {\n                               \"2019-08-01T15:20:12\": 6.3,\n\t\t\t\t\"2019-08-01T15:44:12\": null,\n\t\t\t\t\"2019-08-03T16:20:15\": 5.4,\n\t\t\t\t\"2019-08-05T12:00:34\": 5.6\n             },\n            \"second\": {\n                                \"2019-08-01T15:20:12\": 59.5,\n\t\t\t\t \"2019-08-01T15:44:12\": 9.4,\n\t\t\t\t \"2019-08-03T16:20:15\": 26.1,\n\t\t\t\t \"2019-08-05T12:00:34\": 12.6\n             }\n\t}\n```\n",
  "id": "2abf72f6-68c9-7398-7175-165d31b3ced7",
  "io_interface": {
    "inputs": [
      {
        "data_type": "ANY",
        "id": "a329b531-6fd7-fc1b-cd99-9e3eac95f7ee",
        "name": "a",
        "type": "REQUIRED"
      },
      {
        "data_type": "ANY",
        "id": "97f7df43-bfb5-554a-4ba7-f3fc85a468b6",
        "name": "b",
        "type": "REQUIRED"
      }
    ],
    "outputs": [
      {
        "data_type": "ANY",
        "id": "1dde5f5d-178b-aa88-be6a-8fe1bb59cd27",
        "name": "sum"
      }
    ]
  },
  "name": "Add",
  "release_wiring": {
    "dashboard_positionings": [],
    "input_wirings": [],
    "output_wirings": []
  },
  "released_timestamp": "2022-02-09T17:33:32.478184+00:00",
  "revision_group_id": "2abf72f6-68c9-7398-7175-165d31b3ced7",
  "state": "RELEASED",
  "test_wiring": {
    "dashboard_positionings": [],
    "input_wirings": [],
    "output_wirings": []
  },
  "type": "COMPONENT",
  "version_tag": "1.0.0"
}