{
  "category": "Basic Arithmetic",
  "content": "\"\"\"Documentation for Multiply\n\n# Multiply\n\n## Description\nThis component multiplies numeric values, Pandas Series and Pandas DataFrames.\n\n## Inputs\n* **a** (Integer, Float, Pandas Series or Pandas DataFrame): Entries must be numeric.\n* **b** (Integer, Float, Pandas Series or Pandas DataFrame): Entries must be numeric.\n\n## Outputs\n* **product** (Integer, Float, Pandas Series or Pandas DataFrame): The product of a and b.\n\n## Details\nThe component multiplies a and b. \n\n## Examples\nThe json input of a typical call of this component with two Pandas Series is\n```\n{\n\t\"a\": {\n\t\t\t\t\"2019-08-01T15:20:12\": 3.0,\n\t\t\t\t\"2019-08-01T15:44:12\": 0.0,\n\t\t\t\t\"2019-08-03T16:20:15\": 5.0,\n\t\t\t\t\"2019-08-05T12:00:34\": 0.5,\n                               \"2019-08-07T11:01:00\": 7.0\n\t},\n\t\"b\": {\n\t\t\t\t\"2019-08-01T15:20:12\": 1.0,\n\t\t\t\t\"2019-08-01T15:44:12\": 2.5,\n\t\t\t\t\"2019-08-03T16:20:15\": 3.0,\n\t\t\t\t\"2019-08-05T12:00:34\": 5.0    \n\t}\n}\n```\nThe expected output is\n```\n\t\"product\": {\n\t\t\t\"2019-08-01T15:20:12\": 3,\n\t\t\t\"2019-08-01T15:44:12\": 0,\n\t\t\t\"2019-08-03T16:20:15\": 15,\n\t\t\t\"2019-08-05T12:00:34\": 2.5,\n                       \"2019-08-07T11:01:00\": null\n\t}\n\n```\n\nThe json input of a typical call of this component with a Float and a Pandas DataFrame is\n```\n{\n\t\"a\": 5.0\n    \"b\": {\n\t\t\t\"first\": {\n                               \"2019-08-01T15:20:12\": 1.2,\n\t\t\t\t\"2019-08-01T15:44:12\": null,\n\t\t\t\t\"2019-08-03T16:20:15\": 0.3,\n\t\t\t\t\"2019-08-05T12:00:34\": 0.5\n             },\n            \"second\": {\n                                \"2019-08-01T15:20:12\": 54.4,\n\t\t\t\t \"2019-08-01T15:44:12\": 4.3,\n\t\t\t\t \"2019-08-03T16:20:15\": 21.0,\n\t\t\t\t \"2019-08-05T12:00:34\": 7.5\n             }\n\t}\n}\n```\nThe expected output is\n```\n\t\"product\": {\n\t\t\t\"first\": {\n                               \"2019-08-01T15:20:12\": 6,\n\t\t\t\t\"2019-08-01T15:44:12\": null,\n\t\t\t\t\"2019-08-03T16:20:15\": 1.5,\n\t\t\t\t\"2019-08-05T12:00:34\": 2.5\n             },\n            \"second\": {\n                                \"2019-08-01T15:20:12\": 272,\n\t\t\t\t \"2019-08-01T15:44:12\": 21.5,\n\t\t\t\t \"2019-08-03T16:20:15\": 105,\n\t\t\t\t \"2019-08-05T12:00:34\": 37.5\n             }\n\t}\n```\n\"\"\"\n\nimport pandas as pd\n\n# ***** DO NOT EDIT LINES BELOW *****\n# These lines may be overwritten if component details or inputs/outputs change.\nCOMPONENT_INFO = {\n    \"inputs\": {\n        \"a\": {\"data_type\": \"ANY\"},\n        \"b\": {\"data_type\": \"ANY\"},\n    },\n    \"outputs\": {\n        \"product\": {\"data_type\": \"ANY\"},\n    },\n    \"name\": \"Multiply\",\n    \"category\": \"Basic Arithmetic\",\n    \"description\": \"Multiplies a and b\",\n    \"version_tag\": \"1.0.0\",\n    \"id\": \"0438da97-f524-4a68-28c9-a88c81aa2c63\",\n    \"revision_group_id\": \"0438da97-f524-4a68-28c9-a88c81aa2c63\",\n    \"state\": \"RELEASED\",\n    \"released_timestamp\": \"2022-02-09T17:33:32.663533+00:00\",\n}\n\nfrom hdutils import parse_default_value  # noqa: E402, F401\n\n\ndef main(*, a, b):\n    # entrypoint function for this component\n    # ***** DO NOT EDIT LINES ABOVE *****\n    # write your function code here.\n    return {\"product\": (a * b)}\n\n\nTEST_WIRING_FROM_PY_FILE_IMPORT = {}\nRELEASE_WIRING = {}\n",
  "description": "Multiplies a and b",
  "documentation": "# Multiply\n\n## Description\nThis component multiplies numeric values, Pandas Series and Pandas DataFrames.\n\n## Inputs\n* **a** (Integer, Float, Pandas Series or Pandas DataFrame): Entries must be numeric.\n* **b** (Integer, Float, Pandas Series or Pandas DataFrame): Entries must be numeric.\n\n## Outputs\n* **product** (Integer, Float, Pandas Series or Pandas DataFrame): The product of a and b.\n\n## Details\nThe component multiplies a and b. \n\n## Examples\nThe json input of a typical call of this component with two Pandas Series is\n```\n{\n\t\"a\": {\n\t\t\t\t\"2019-08-01T15:20:12\": 3.0,\n\t\t\t\t\"2019-08-01T15:44:12\": 0.0,\n\t\t\t\t\"2019-08-03T16:20:15\": 5.0,\n\t\t\t\t\"2019-08-05T12:00:34\": 0.5,\n                               \"2019-08-07T11:01:00\": 7.0\n\t},\n\t\"b\": {\n\t\t\t\t\"2019-08-01T15:20:12\": 1.0,\n\t\t\t\t\"2019-08-01T15:44:12\": 2.5,\n\t\t\t\t\"2019-08-03T16:20:15\": 3.0,\n\t\t\t\t\"2019-08-05T12:00:34\": 5.0    \n\t}\n}\n```\nThe expected output is\n```\n\t\"product\": {\n\t\t\t\"2019-08-01T15:20:12\": 3,\n\t\t\t\"2019-08-01T15:44:12\": 0,\n\t\t\t\"2019-08-03T16:20:15\": 15,\n\t\t\t\"2019-08-05T12:00:34\": 2.5,\n                       \"2019-08-07T11:01:00\": null\n\t}\n\n```\n\nThe json input of a typical call of this component with a Float and a Pandas DataFrame is\n```\n{\n\t\"a\": 5.0\n    \"b\": {\n\t\t\t\"first\": {\n                               \"2019-08-01T15:20:12\": 1.2,\n\t\t\t\t\"2019-08-01T15:44:12\": null,\n\t\t\t\t\"2019-08-03T16:20:15\": 0.3,\n\t\t\t\t\"2019-08-05T12:00:34\": 0.5\n             },\n            \"second\": {\n                                \"2019-08-01T15:20:12\": 54.4,\n\t\t\t\t \"2019-08-01T15:44:12\": 4.3,\n\t\t\t\t \"2019-08-03T16:20:15\": 21.0,\n\t\t\t\t \"2019-08-05T12:00:34\": 7.5\n             }\n\t}\n}\n```\nThe expected output is\n```\n\t\"product\": {\n\t\t\t\"first\": {\n                               \"2019-08-01T15:20:12\": 6,\n\t\t\t\t\"2019-08-01T15:44:12\": null,\n\t\t\t\t\"2019-08-03T16:20:15\": 1.5,\n\t\t\t\t\"2019-08-05T12:00:34\": 2.5\n             },\n            \"second\": {\n                                \"2019-08-01T15:20:12\": 272,\n\t\t\t\t \"2019-08-01T15:44:12\": 21.5,\n\t\t\t\t \"2019-08-03T16:20:15\": 105,\n\t\t\t\t \"2019-08-05T12:00:34\": 37.5\n             }\n\t}\n```\n",
  "id": "0438da97-f524-4a68-28c9-a88c81aa2c63",
  "io_interface": {
    "inputs": [
      {
        "data_type": "ANY",
        "id": "61a078bc-e8e2-3b9f-34b3-07507885f3f3",
        "name": "a",
        "type": "REQUIRED"
      },
      {
        "data_type": "ANY",
        "id": "c9a07403-6a18-5562-c19c-247d76abcf36",
        "name": "b",
        "type": "REQUIRED"
      }
    ],
    "outputs": [
      {
        "data_type": "ANY",
        "id": "5f9428b2-948a-5739-4e83-5da58092fc7e",
        "name": "product"
      }
    ]
  },
  "name": "Multiply",
  "release_wiring": {
    "dashboard_positionings": [],
    "input_wirings": [],
    "output_wirings": []
  },
  "released_timestamp": "2022-02-09T17:33:32.663533+00:00",
  "revision_group_id": "0438da97-f524-4a68-28c9-a88c81aa2c63",
  "state": "RELEASED",
  "test_wiring": {
    "dashboard_positionings": [],
    "input_wirings": [],
    "output_wirings": []
  },
  "type": "COMPONENT",
  "version_tag": "1.0.0"
}