{
  "category": "Basic Arithmetic",
  "content": "\"\"\"Documentation for Round\n\n# Round\n\n## Description\nThis component rounds values with specified number of decimals.\n\n## Inputs\n* **data** (Integer, Float, Pandas Series or Pandas DataFrame): Entries must be numeric.\n* **decimals** (Integer): Number of decimals.\n\n## Outputs\n* **rounded** (Integer, Float, Pandas Series or Pandas DataFrame): Rounded data.\n\n## Details\nThis component rounds values with specified number of decimals.\n\n## Examples\nThe json input of a typical call of this component with a Pandas Series is\n```\n{\n\t\"data\": {\n\t\t\t\t\"2019-08-01T15:20:12\": 4.54154,\n\t\t\t\t\"2019-08-01T15:44:12\": -9.4854,\n\t\t\t\t\"2019-08-03T16:20:15\": 0.420,\n\t\t\t\t\"2019-08-05T12:00:34\": null,\n                               \"2019-08-07T11:01:00\": 100.1202\n\t},\n\t\"decimals\" = 2\n}\n```\nThe expected output is\n```\n\t\"rounded\": {\n\t\t\t\t\"2019-08-01T15:20:12\": 4.54,\n\t\t\t\t\"2019-08-01T15:44:12\": -9.49,\n\t\t\t\t\"2019-08-03T16:20:15\": 0.42,\n\t\t\t\t\"2019-08-05T12:00:34\": null,\n                               \"2019-08-07T11:01:00\": 100.12\n\t}\n```\n\"\"\"\n\nimport pandas as pd\nimport numpy as np\n\n# ***** DO NOT EDIT LINES BELOW *****\n# These lines may be overwritten if component details or inputs/outputs change.\nCOMPONENT_INFO = {\n    \"inputs\": {\n        \"data\": {\"data_type\": \"ANY\"},\n        \"decimals\": {\"data_type\": \"INT\"},\n    },\n    \"outputs\": {\n        \"rounded\": {\"data_type\": \"ANY\"},\n    },\n    \"name\": \"Round\",\n    \"category\": \"Basic Arithmetic\",\n    \"description\": \"Rounds values with specified number of decimals\",\n    \"version_tag\": \"1.0.0\",\n    \"id\": \"50220962-16c0-c94f-8f0a-1e57d76e6878\",\n    \"revision_group_id\": \"50220962-16c0-c94f-8f0a-1e57d76e6878\",\n    \"state\": \"RELEASED\",\n    \"released_timestamp\": \"2022-02-09T17:33:32.390855+00:00\",\n}\n\nfrom hdutils import parse_default_value  # noqa: E402, F401\n\n\ndef main(*, data, decimals):\n    # entrypoint function for this component\n    # ***** DO NOT EDIT LINES ABOVE *****\n    # write your function code here.\n\n    return {\"rounded\": round(data, decimals)}\n\n\nTEST_WIRING_FROM_PY_FILE_IMPORT = {}\nRELEASE_WIRING = {}\n",
  "description": "Rounds values with specified number of decimals",
  "documentation": "# Round\n\n## Description\nThis component rounds values with specified number of decimals.\n\n## Inputs\n* **data** (Integer, Float, Pandas Series or Pandas DataFrame): Entries must be numeric.\n* **decimals** (Integer): Number of decimals.\n\n## Outputs\n* **rounded** (Integer, Float, Pandas Series or Pandas DataFrame): Rounded data.\n\n## Details\nThis component rounds values with specified number of decimals.\n\n## Examples\nThe json input of a typical call of this component with a Pandas Series is\n```\n{\n\t\"data\": {\n\t\t\t\t\"2019-08-01T15:20:12\": 4.54154,\n\t\t\t\t\"2019-08-01T15:44:12\": -9.4854,\n\t\t\t\t\"2019-08-03T16:20:15\": 0.420,\n\t\t\t\t\"2019-08-05T12:00:34\": null,\n                               \"2019-08-07T11:01:00\": 100.1202\n\t},\n\t\"decimals\" = 2\n}\n```\nThe expected output is\n```\n\t\"rounded\": {\n\t\t\t\t\"2019-08-01T15:20:12\": 4.54,\n\t\t\t\t\"2019-08-01T15:44:12\": -9.49,\n\t\t\t\t\"2019-08-03T16:20:15\": 0.42,\n\t\t\t\t\"2019-08-05T12:00:34\": null,\n                               \"2019-08-07T11:01:00\": 100.12\n\t}\n```\n",
  "id": "50220962-16c0-c94f-8f0a-1e57d76e6878",
  "io_interface": {
    "inputs": [
      {
        "data_type": "ANY",
        "id": "af913fee-f47d-7ece-99bb-865d4756b8d4",
        "name": "data",
        "type": "REQUIRED"
      },
      {
        "data_type": "INT",
        "id": "411c4761-1ae8-481f-2e59-f8882c6e044e",
        "name": "decimals",
        "type": "REQUIRED"
      }
    ],
    "outputs": [
      {
        "data_type": "ANY",
        "id": "1189d4f3-2d77-065b-1416-fe19a0b615ff",
        "name": "rounded"
      }
    ]
  },
  "name": "Round",
  "release_wiring": {
    "dashboard_positionings": [],
    "input_wirings": [],
    "output_wirings": []
  },
  "released_timestamp": "2022-02-09T17:33:32.390855+00:00",
  "revision_group_id": "50220962-16c0-c94f-8f0a-1e57d76e6878",
  "state": "RELEASED",
  "test_wiring": {
    "dashboard_positionings": [],
    "input_wirings": [],
    "output_wirings": []
  },
  "type": "COMPONENT",
  "version_tag": "1.0.0"
}