{
  "category": "Basic Arithmetic",
  "content": "\"\"\"Documentation for Signum\n\n# Signum\n\n## Description\nThis component calculates the signum of the input.\n\n## Inputs\n* **data** (Integer, Float, Pandas Series or Pandas DataFrame): Entries must be numeric.\n\n## Outputs\n* **absolute** (Integer, Float, Pandas Series or Pandas DataFrame): Signum of data.\n\n## Details\nThe component calculates the signum of the input. \n\n## Examples\nThe json input of a typical call of this component with a Pandas Series is\n```\n{\n\t\"data\": {\n\t\t\t\t\"2019-08-01T15:20:12\": 4,\n\t\t\t\t\"2019-08-01T15:44:12\": -9,\n\t\t\t\t\"2019-08-03T16:20:15\": 0,\n\t\t\t\t\"2019-08-05T12:00:34\": null,\n                \"2019-08-07T11:01:00\": -100\n\t}\n}\n```\nThe expected output is\n```\n\t\"absolute\": {\n\t\t\t\t\"2019-08-01T15:20:12\": 1,\n\t\t\t\t\"2019-08-01T15:44:12\": -1,\n\t\t\t\t\"2019-08-03T16:20:15\": 0,\n\t\t\t\t\"2019-08-05T12:00:34\": null,\n                \"2019-08-07T11:01:00\": -1\n\t}\n\n```\n\"\"\"\n\nimport pandas as pd\nimport numpy as np\n\n# ***** DO NOT EDIT LINES BELOW *****\n# These lines may be overwritten if component details or inputs/outputs change.\nCOMPONENT_INFO = {\n    \"inputs\": {\n        \"data\": {\"data_type\": \"ANY\"},\n    },\n    \"outputs\": {\n        \"signum\": {\"data_type\": \"ANY\"},\n    },\n    \"name\": \"Signum\",\n    \"category\": \"Basic Arithmetic\",\n    \"description\": \"Returns sign of the input\",\n    \"version_tag\": \"1.0.0\",\n    \"id\": \"24f115a8-45ad-21f2-c6ce-8edfc28f3b3f\",\n    \"revision_group_id\": \"24f115a8-45ad-21f2-c6ce-8edfc28f3b3f\",\n    \"state\": \"RELEASED\",\n    \"released_timestamp\": \"2022-02-09T17:33:32.343501+00:00\",\n}\n\nfrom hdutils import parse_default_value  # noqa: E402, F401\n\n\ndef main(*, data):\n    # entrypoint function for this component\n    # ***** DO NOT EDIT LINES ABOVE *****\n    # write your function code here.\n\n    return {\"signum\": np.sign(data)}\n\n\nTEST_WIRING_FROM_PY_FILE_IMPORT = {}\nRELEASE_WIRING = {}\n",
  "description": "Returns sign of the input",
  "documentation": "# Signum\n\n## Description\nThis component calculates the signum of the input.\n\n## Inputs\n* **data** (Integer, Float, Pandas Series or Pandas DataFrame): Entries must be numeric.\n\n## Outputs\n* **absolute** (Integer, Float, Pandas Series or Pandas DataFrame): Signum of data.\n\n## Details\nThe component calculates the signum of the input. \n\n## Examples\nThe json input of a typical call of this component with a Pandas Series is\n```\n{\n\t\"data\": {\n\t\t\t\t\"2019-08-01T15:20:12\": 4,\n\t\t\t\t\"2019-08-01T15:44:12\": -9,\n\t\t\t\t\"2019-08-03T16:20:15\": 0,\n\t\t\t\t\"2019-08-05T12:00:34\": null,\n                \"2019-08-07T11:01:00\": -100\n\t}\n}\n```\nThe expected output is\n```\n\t\"absolute\": {\n\t\t\t\t\"2019-08-01T15:20:12\": 1,\n\t\t\t\t\"2019-08-01T15:44:12\": -1,\n\t\t\t\t\"2019-08-03T16:20:15\": 0,\n\t\t\t\t\"2019-08-05T12:00:34\": null,\n                \"2019-08-07T11:01:00\": -1\n\t}\n\n```\n",
  "id": "24f115a8-45ad-21f2-c6ce-8edfc28f3b3f",
  "io_interface": {
    "inputs": [
      {
        "data_type": "ANY",
        "id": "8ae9aed6-8009-2aa6-1b2e-d991c6535e90",
        "name": "data",
        "type": "REQUIRED"
      }
    ],
    "outputs": [
      {
        "data_type": "ANY",
        "id": "2e6a7af0-898a-2e5f-06b8-8c740b06f8f0",
        "name": "signum"
      }
    ]
  },
  "name": "Signum",
  "release_wiring": {
    "dashboard_positionings": [],
    "input_wirings": [],
    "output_wirings": []
  },
  "released_timestamp": "2022-02-09T17:33:32.343501+00:00",
  "revision_group_id": "24f115a8-45ad-21f2-c6ce-8edfc28f3b3f",
  "state": "RELEASED",
  "test_wiring": {
    "dashboard_positionings": [],
    "input_wirings": [],
    "output_wirings": []
  },
  "type": "COMPONENT",
  "version_tag": "1.0.0"
}