{
  "category": "Basic Arithmetic",
  "content": "\"\"\"Documentation for Substract\n\n# Substract\n\n## Description\nThis component subtracts numeric values, Pandas Series and Pandas DataFrames.\n\n## Inputs\n* **a** (Integer, Float, Pandas Series or Pandas DataFrame): Entries must be numeric.\n* **b** (Integer, Float, Pandas Series or Pandas DataFrame): Entries must be numeric.\n\n## Outputs\n* **difference** (Integer, Float, Pandas Series or Pandas DataFrame): The difference of a and b. \n\n## Details\nThe component calculates the difference of a and b.\n\n## Examples\nThe json input of a typical call of this component with two Pandas Series is\n```\n{\n\t\"a\": {\n\t\t\t\t\"2019-08-01T15:20:12\": 1.2,\n\t\t\t\t\"2019-08-01T15:44:12\": 0.0,\n\t\t\t\t\"2019-08-03T16:20:15\": 0.3,\n\t\t\t\t\"2019-08-05T12:00:34\": 0.5,\n                \"2019-08-07T11:01:00\": 7.8\n\t},\n\t\"b\": {\n\t\t\t\t\"2019-08-01T15:20:12\": 1.4,\n\t\t\t\t\"2019-08-01T15:44:12\": 2.6,\n\t\t\t\t\"2019-08-03T16:20:15\": 3.8,\n\t\t\t\t\"2019-08-05T12:00:34\": 5.0    \n\t}\n}\n```\nThe expected output is\n```\n\t\"difference\": {\n\t\t\t\"2019-08-01T15:20:12\": -0.2\n\t\t\t\"2019-08-01T15:44:12\": -2.6,\n\t\t\t\"2019-08-03T16:20:15\": -3.5,\n\t\t\t\"2019-08-05T12:00:34\": -4.5,\n            \"2019-08-07T11:01:00\":  null  \n\t}\n\n```\n\nThe json input of a typical call of this component with a Float and a Pandas DataFrame is\n```\n{\n\t\"a\": 5.1\n    \"b\": {\n\t\t\t\"first\": {\n                \"2019-08-01T15:20:12\": 1.2,\n\t\t\t\t\"2019-08-01T15:44:12\": null,\n\t\t\t\t\"2019-08-03T16:20:15\": 0.3,\n\t\t\t\t\"2019-08-05T12:00:34\": 0.5\n             },\n            \"second\": {\n                 \"2019-08-01T15:20:12\": 54.4,\n\t\t\t\t \"2019-08-01T15:44:12\": 4.3,\n\t\t\t\t \"2019-08-03T16:20:15\": 21.0,\n\t\t\t\t \"2019-08-05T12:00:34\": 7.5\n             }\n\t}\n}\n```\nThe expected output is\n```\n\t\"difference\": {\n\t\t\t\"first\": {\n                \"2019-08-01T15:20:12\": 3.9,\n\t\t\t\t\"2019-08-01T15:44:12\": null,\n\t\t\t\t\"2019-08-03T16:20:15\": 4.8,\n\t\t\t\t\"2019-08-05T12:00:34\": 4.6\n             },\n            \"second\": {\n                 \"2019-08-01T15:20:12\": -49.3,\n\t\t\t\t \"2019-08-01T15:44:12\": 0.8,\n\t\t\t\t \"2019-08-03T16:20:15\": -16.9,\n\t\t\t\t \"2019-08-05T12:00:34\": -2.4\n             }\n\t}\n```\n\"\"\"\n\nimport pandas as pd\n\n# ***** DO NOT EDIT LINES BELOW *****\n# These lines may be overwritten if component details or inputs/outputs change.\nCOMPONENT_INFO = {\n    \"inputs\": {\n        \"a\": {\"data_type\": \"ANY\"},\n        \"b\": {\"data_type\": \"ANY\"},\n    },\n    \"outputs\": {\n        \"difference\": {\"data_type\": \"ANY\"},\n    },\n    \"name\": \"Substract\",\n    \"category\": \"Basic Arithmetic\",\n    \"description\": \"Subtracts b from a\",\n    \"version_tag\": \"1.0.0\",\n    \"id\": \"10d27d69-e999-6654-3cef-427672aeb0fa\",\n    \"revision_group_id\": \"10d27d69-e999-6654-3cef-427672aeb0fa\",\n    \"state\": \"RELEASED\",\n    \"released_timestamp\": \"2022-02-09T17:33:32.445565+00:00\",\n}\n\nfrom hdutils import parse_default_value  # noqa: E402, F401\n\n\ndef main(*, a, b):\n    # entrypoint function for this component\n    # ***** DO NOT EDIT LINES ABOVE *****\n    # write your function code here.\n\n    return {\"difference\": (a - b)}\n\n\nTEST_WIRING_FROM_PY_FILE_IMPORT = {}\nRELEASE_WIRING = {}\n",
  "description": "Subtracts b from a",
  "documentation": "# Substract\n\n## Description\nThis component subtracts numeric values, Pandas Series and Pandas DataFrames.\n\n## Inputs\n* **a** (Integer, Float, Pandas Series or Pandas DataFrame): Entries must be numeric.\n* **b** (Integer, Float, Pandas Series or Pandas DataFrame): Entries must be numeric.\n\n## Outputs\n* **difference** (Integer, Float, Pandas Series or Pandas DataFrame): The difference of a and b. \n\n## Details\nThe component calculates the difference of a and b.\n\n## Examples\nThe json input of a typical call of this component with two Pandas Series is\n```\n{\n\t\"a\": {\n\t\t\t\t\"2019-08-01T15:20:12\": 1.2,\n\t\t\t\t\"2019-08-01T15:44:12\": 0.0,\n\t\t\t\t\"2019-08-03T16:20:15\": 0.3,\n\t\t\t\t\"2019-08-05T12:00:34\": 0.5,\n                \"2019-08-07T11:01:00\": 7.8\n\t},\n\t\"b\": {\n\t\t\t\t\"2019-08-01T15:20:12\": 1.4,\n\t\t\t\t\"2019-08-01T15:44:12\": 2.6,\n\t\t\t\t\"2019-08-03T16:20:15\": 3.8,\n\t\t\t\t\"2019-08-05T12:00:34\": 5.0    \n\t}\n}\n```\nThe expected output is\n```\n\t\"difference\": {\n\t\t\t\"2019-08-01T15:20:12\": -0.2\n\t\t\t\"2019-08-01T15:44:12\": -2.6,\n\t\t\t\"2019-08-03T16:20:15\": -3.5,\n\t\t\t\"2019-08-05T12:00:34\": -4.5,\n            \"2019-08-07T11:01:00\":  null  \n\t}\n\n```\n\nThe json input of a typical call of this component with a Float and a Pandas DataFrame is\n```\n{\n\t\"a\": 5.1\n    \"b\": {\n\t\t\t\"first\": {\n                \"2019-08-01T15:20:12\": 1.2,\n\t\t\t\t\"2019-08-01T15:44:12\": null,\n\t\t\t\t\"2019-08-03T16:20:15\": 0.3,\n\t\t\t\t\"2019-08-05T12:00:34\": 0.5\n             },\n            \"second\": {\n                 \"2019-08-01T15:20:12\": 54.4,\n\t\t\t\t \"2019-08-01T15:44:12\": 4.3,\n\t\t\t\t \"2019-08-03T16:20:15\": 21.0,\n\t\t\t\t \"2019-08-05T12:00:34\": 7.5\n             }\n\t}\n}\n```\nThe expected output is\n```\n\t\"difference\": {\n\t\t\t\"first\": {\n                \"2019-08-01T15:20:12\": 3.9,\n\t\t\t\t\"2019-08-01T15:44:12\": null,\n\t\t\t\t\"2019-08-03T16:20:15\": 4.8,\n\t\t\t\t\"2019-08-05T12:00:34\": 4.6\n             },\n            \"second\": {\n                 \"2019-08-01T15:20:12\": -49.3,\n\t\t\t\t \"2019-08-01T15:44:12\": 0.8,\n\t\t\t\t \"2019-08-03T16:20:15\": -16.9,\n\t\t\t\t \"2019-08-05T12:00:34\": -2.4\n             }\n\t}\n```",
  "id": "10d27d69-e999-6654-3cef-427672aeb0fa",
  "io_interface": {
    "inputs": [
      {
        "data_type": "ANY",
        "id": "70a510ea-ae96-d1cd-7135-25bc41e65bb6",
        "name": "a",
        "type": "REQUIRED"
      },
      {
        "data_type": "ANY",
        "id": "ba67d6e1-4a1a-8a02-0a55-cf8731e01734",
        "name": "b",
        "type": "REQUIRED"
      }
    ],
    "outputs": [
      {
        "data_type": "ANY",
        "id": "4c60ecbd-35e4-e78c-6569-f4b26365c565",
        "name": "difference"
      }
    ]
  },
  "name": "Substract",
  "release_wiring": {
    "dashboard_positionings": [],
    "input_wirings": [],
    "output_wirings": []
  },
  "released_timestamp": "2022-02-09T17:33:32.445565+00:00",
  "revision_group_id": "10d27d69-e999-6654-3cef-427672aeb0fa",
  "state": "RELEASED",
  "test_wiring": {
    "dashboard_positionings": [],
    "input_wirings": [],
    "output_wirings": []
  },
  "type": "COMPONENT",
  "version_tag": "1.0.0"
}